Workbook

Sheet README
A1: 06 — Cost & Traceability Model (INR) — in-house commerce-intelligence app (Rama / Phoenix) — v0.3
A3: Purpose: editable planning model for build cost (labour by work package), CapEx-candidate / expense boundary, monthly OpEx, TCO (12/24/36 months), build-vs-buy vs Sellerboard, sensitivity and WP→release→feature traceability.
A5: Version 0.3 — audit cutoff 2026-10-10 (baseline v0.1 cutoff 2026-09-10). Scope source: /engineering/scope_register.json (36 work packages WP-01..WP-39 with WP-18/19/21 retired, 11,180 h; releases R0–R5 with calendar_weeks; 31 connectors; 172 features). Regenerate with /engineering/build_cost_model.py. Price sources: /research/public_sources_apis.md.
A7: ALL RATES AND ALLOWANCES ARE PLANNING ASSUMPTIONS, NOT QUOTES. No vendor, contractor or cloud provider has quoted these figures. Hourly rates are labelled assumptions for an Indian in-house / contract team; validate before approval.
A9: Colour legend: BLUE text = input / assumption you may change; BLACK text = formula (do not overwrite); GREEN text = link to another sheet; YELLOW fill = key decision inputs (contingency %, capitalization approved %, benefit threshold).
A11: How to change assumptions: edit BLUE cells on 'Assumptions' (rates, contingency, FTE capacity, FX, cloud, AI tokens, Sellerboard spend, scenario multipliers) and on 'WorkPackages' (hours per WP), and the category % inputs on 'Accounting_Boundary'. Every other sheet recalculates. Do not insert rows inside the rate table (rows referenced by VLOOKUP). To change scope, edit scope_register.json and re-run the build script.
A13: Sheets: Assumptions · WorkPackages · Build_Summary · Capacity_Schedule · OpEx_Monthly (with applies_from_release) · TCO · Accounting_Boundary · Build_vs_Buy · Sensitivity · Traceability · Features_Ref (data extract used by Traceability counts) · Verification (key totals, LibreOffice-recalc verified) · Change_v02_v03 (v0.2 vs v0.3 bridge and the WPs that drove it).
A15: Key conventions: hours × loaded rate = labour cost; cash TCO includes the 20% contingency as committed budget; it is shown separately in Build_Summary; 'Initial bounded release' = R0+R1 plus a pro-rata share of cross-cutting (ALL) WPs by hours; 'Full approved parity' = all WPs. Amortization is shown separately from cash and is never added to cash TCO. Capitalization is a CFO decision under Ind AS 38 / IAS 38 — default approved % is 0.
A17: What changed in v0.3 (2026-10-10, Owner decisions): (1) marketing function omitted — WP-18 review requests, WP-19 PPC analytics and WP-21 PPC automation retired; WP-14 reduced to LTV/repeat customers (220 h); WP-20 safety framework reduced to repricer writes (280 h); ad spend is still read (WP-37, R1) as a cost line so net profit matches Sellerboard. (2) All markets — every Amazon marketplace (new WP-38, R2) and Walmart/eBay/TikTok Shop (WP-23 moved R5→R2, 600 h); ops connectors split to new WP-39 (R5). (3) Build with ChatGPT Codex; deploy on AWS. R2 is now 'All markets & marketplaces' (14 weeks); R4 'Pricing automation (conditional)' (6 weeks); R5 10 weeks. See Change_v02_v03.
A18: Earlier — what changed in v0.2: R1 widened to 'India-first unified profit core' (14 weeks, was 10): WP-12 Shopify connector and WP-13 fee profiles moved R2→R1; new R1 WPs WP-31 (B2B sales), WP-32 (unified dashboard), WP-33 (mobile-first PWA shell), WP-34 (Sellerboard-compatible P&L + parallel run), WP-35 (Shopify cost completeness); new WP-36 (multi-entity consolidation) in R2; WP-24 reduced to 220 h. New OpEx line 'Courier/3PL data handling' (₹0 assumption, from R1). Sellerboard spend now 3 accounts on sellerboard.com + 1 Shopify store on sellerboard.io.
A19: Excluded from all figures: ad spend, stock purchases, fulfilment fees, GST/taxes on services, office overhead, recruitment. SP-API fees: Amazon cancelled the planned fees 'at this time' (May 2026) → $0 planning assumption, monitor.
A20: Sellerboard reference: sellerboard.com Business plan $39/mo observed (3 accounts); other .com plans $19–$79/mo per account. sellerboard.io (Shopify store, 1 store): plan NOT observed → $39/mo is an ASSUMPTION, labelled on Assumptions.

Sheet Assumptions
A1: Assumptions — all BLUE cells are planning assumptions, not quotes
A2: Units: INR unless stated. Cutoff 2026-10-10. Scope register v0.3.
A4: Loaded hourly rate by role (INR/h) | B4: Value | C4: Unit | D4: Note
A5: Solution architect | B5: 3500 | C5: INR/h | D5: Assumption — loaded (salary + overhead) India rate; not a quote
A6: Backend lead | B6: 3000 | C6: INR/h | D6: Assumption — loaded (salary + overhead) India rate; not a quote
A7: Backend | B7: 2400 | C7: INR/h | D7: Assumption — loaded (salary + overhead) India rate; not a quote
A8: Frontend | B8: 2200 | C8: INR/h | D8: Assumption — loaded (salary + overhead) India rate; not a quote
A9: Full-stack | B9: 2400 | C9: INR/h | D9: Assumption — loaded (salary + overhead) India rate; not a quote
A10: Integration eng | B10: 2600 | C10: INR/h | D10: Assumption — loaded (salary + overhead) India rate; not a quote
A11: Financial/data eng | B11: 2600 | C11: INR/h | D11: Assumption — loaded (salary + overhead) India rate; not a quote
A12: Data eng | B12: 2400 | C12: INR/h | D12: Assumption — loaded (salary + overhead) India rate; not a quote
A13: Product designer | B13: 2000 | C13: INR/h | D13: Assumption — loaded (salary + overhead) India rate; not a quote
A14: QA/security | B14: 1800 | C14: INR/h | D14: Assumption — loaded (salary + overhead) India rate; not a quote
A15: DevOps | B15: 2400 | C15: INR/h | D15: Assumption — loaded (salary + overhead) India rate; not a quote
A16: Delivery lead | B16: 3000 | C16: INR/h | D16: Assumption — loaded (salary + overhead) India rate; not a quote
A18: Delivery & capacity | B18: Value | C18: Unit | D18: Note
A19: Contingency % on labour | B19: 0.2 | C19: % | D19: Committed budget in cash TCO; shown separately in Build_Summary
A20: Nominal FTE capacity | B20: 160 | C20: h/month | D20: Assumption
A21: Productive factor | B21: 0.75 | C21: ratio | D21: Share of nominal hours that is productive delivery
A22: USD→INR | B22: 84 | C22: INR per USD | D22: Assumption; refresh at approval date
A23: Amortization period (capex-candidate) | B23: 3 | C23: years | D23: Straight-line; shown separately from cash
A25: Release calendar (from scope_register.json calendar_weeks) | B25: Value | C25: Unit | D25: Note
A26: R0 — Read-only pilot & foundations | B26: 8 | C26: weeks | D26: Workspace, entities, connectors read-only, raw ledger, 90-day backfill, no operational writes
A27: R1 — India-first unified profit core | B27: 14 | C27: weeks | D27: One dashboard for Amazon.in + Shopify India + manual B2B: Sellerboard-compatible P&L, COGS, fees, expenses, B2B entry, reports, mobile-first UI, parallel-run reconciliation
A28: R2 — All markets & marketplaces | B28: 14 | C28: weeks | D28: UK/US/FR/DE entities and stores, every other Amazon marketplace (NA/EU/FE regions), Walmart US/CA/MX, eBay, TikTok Shop; multi-entity consolidation with FX & intercompany elimination; LTV & repeat customers; B2B receivables/export
A29: R3 — Operations | B29: 10 | C29: weeks | D29: Inventory planner, POs, suppliers, FBA/WFS shipments, reimbursement candidates (Money Back), alerts, automation safety framework
A30: R4 — Pricing automation (conditional) | B30: 6 | C30: weeks | D30: Repricer contract (simulation-first; writes only after approval, maker-checker, canary, kill switch)
A31: R5 — Extended operations connectors & clients | B31: 10 | C31: weeks | D31: ShipStation/Flexport/SFN/Veeqo/CJ connectors, PWA extras, browser extension, QuickBooks/Tally export & cashflow, optional AI explain layer
A32: ALL — cross-cutting (sum of R0–R5) | B32: =SUM(B26:B31) -> 62 | C32: weeks | D32: Formula: sum of release weeks
A34: Cloud hosting (monthly, INR) | B34: Value | C34: Unit | D34: Note
A35: Compute (app + workers) | B35: 45000 | C35: INR/mo | D35: Assumption
A36: Managed Postgres | B36: 25000 | C36: INR/mo | D36: Assumption
A37: Object storage | B37: 8000 | C37: INR/mo | D37: Assumption
A38: Jobs / queue | B38: 10000 | C38: INR/mo | D38: Assumption
A39: Egress | B39: 5000 | C39: INR/mo | D39: Assumption
A40: Observability | B40: 12000 | C40: INR/mo | D40: Assumption
A41: Backups / DR (cross-region copy to ap-south-2) | B41: 6000 | C41: INR/mo | D41: Assumption
A42: Security / landing zone (GuardDuty, Security Hub, Config, CloudTrail, WAF, KMS) | B42: 18000 | C42: INR/mo | D42: Assumption
A44: Ongoing staff / support | B44: Value | C44: Unit | D44: Note
A45: Support / maintenance FTE | B45: 1 | C45: FTE | D45: Assumption — one engineer part-allocated
A46: Support engineer loaded rate | B46: 2400 | C46: INR/h | D46: Assumption
A47: Support hours per FTE per month | B47: 80 | C47: h/mo | D47: Assumption — 50% of nominal
A48: Support monthly cost | B48: =$B$45*$B$46*$B$47 -> 192000 | C48: INR/mo | D48: Formula = FTE × rate × hours
A49: Provider / API version upgrade allowance | B49: 20000 | C49: INR/mo | D49: Assumption — SP-API, Shopify, Ads API deprecation cycles
A50: Security review (annual) | B50: 300000 | C50: INR/yr | D50: Assumption — external pen-test / review
A51: Optional native / browser-extension upkeep | B51: 40000 | C51: INR/mo | D51: Assumption — set 0 if PWA-only (R5 scope)
A52: Courier/3PL data handling | B52: 0 | C52: INR/mo | D52: ASSUMPTION ₹0 — CSV/XLSX import of courier/3PL invoices (CON-32, WP-35) needs no paid API at cutoff; set a value if an aggregator/API fee is incurred. Applies from R1.
A54: Software / API fees (monthly, INR) | B54: Value | C54: Unit | D54: Note
A55: Amazon SP-API | B55: 0 | C55: INR/mo | D55: Amazon cancelled planned fees 'at this time' (May 2026) → $0; monitor (S35)
A56: Amazon Ads API | B56: 0 | C56: INR/mo | D56: No fee published
A57: Shopify custom app | B57: 0 | C57: INR/mo | D57: Custom app — no listing fee (applies from R1 in v0.2: WP-12 moved to R1)
A58: Other tools (repo, CI, e-mail, monitoring SaaS) | B58: 15000 | C58: INR/mo | D58: Assumption
A59: ChatGPT Business seats with Codex (build team) | B59: 12 | C59: seats | D59: Assumption — v0.3 build tool (DC-16); size to the actual team
A60: ChatGPT Business Standard seat, monthly billing | B60: 25 | C60: USD/seat/mo | D60: OpenAI Help Center, checked 2026-10-10 (S60): $25 monthly / $20 annual per seat, min 2 seats; Standard seats include Codex; usage limits may require Premium seats or credits
A61: ChatGPT/Codex seats monthly | B61: =$B$59*$B$60*$B$22 -> 25200 | C61: INR/mo | D61: Formula = seats × price × FX
A63: AI consumption (Anthropic API, S47) — USD per million tokens | B63: Value | C63: Unit | D63: Note
A64: Input tokens / month (Fable 5.1) | B64: 30 | C64: M tokens | D64: Assumption — explain layer, aggregates only
A65: Output tokens / month (Fable 5.1) | B65: 5 | C65: M tokens | D65: Assumption
A66: Fable 5.1 input price | B66: 10 | C66: USD/MTok | D66: Anthropic pricing at cutoff (S47)
A67: Fable 5.1 output price | B67: 50 | C67: USD/MTok | D67: Anthropic pricing at cutoff (S47)
A68: Sonnet 5 fallback input tokens / month | B68: 10 | C68: M tokens | D68: Assumption — cheaper fallback for routine explains
A69: Sonnet 5 fallback output tokens / month | B69: 2 | C69: M tokens | D69: Assumption
A70: Sonnet 5 input price | B70: 2 | C70: USD/MTok | D70: Anthropic pricing at cutoff
A71: Sonnet 5 output price | B71: 10 | C71: USD/MTok | D71: Anthropic pricing at cutoff
A72: Haiku 4.5 input price (reference only) | B72: 1 | C72: USD/MTok | D72: Not used in base case
A73: Haiku 4.5 output price (reference only) | B73: 5 | C73: USD/MTok | D73: Not used in base case
A74: AI monthly cost (USD) | B74: =$B$64*$B$66+$B$65*$B$67+$B$68*$B$70+$B$69*$B$71 -> 590 | C74: USD/mo | D74: Formula
A75: AI monthly cost (INR) | B75: =$B$74*$B$22 -> 49560 | C75: INR/mo | D75: Formula = USD × FX
A77: One-time non-labour | B77: Value | C77: Unit | D77: Note
A78: Laptops / licences / domain / certificates | B78: 400000 | C78: INR one-time | D78: Assumption
A79: Training (user onboarding, playbooks) | B79: 250000 | C79: INR one-time | D79: Assumption — excludes WP-29 labour
A80: Migration | B80: 0 | C80: INR one-time | D80: Handled by WP-29 hours (labour) — no separate allowance
A82: Benefit & build-vs-buy | B82: Value | C82: Unit | D82: Note
A83: Monthly benefit threshold (INR) | B83: 0 | C83: INR/mo | D83: Default 0 = unproven; enter only evidenced savings/margin gains
A84: Sellerboard (sellerboard.com) spend per account | B84: 39 | C84: USD/mo | D84: OBSERVED — Business plan $39/mo on sellerboard.com; .com plans $19–$79/mo
A85: Sellerboard (sellerboard.com) accounts | B85: 3 | C85: accounts | D85: 3 Amazon accounts on sellerboard.com (per owner, v0.2)
A86: Sellerboard (sellerboard.io) spend per Shopify store | B86: 39 | C86: USD/mo | D86: ASSUMPTION — sellerboard.io plan not observed at cutoff; $39/mo assumed equal to observed .com Business plan
A87: Sellerboard (sellerboard.io) Shopify stores | B87: 1 | C87: stores | D87: 1 Shopify store on sellerboard.io (per owner, v0.2)
A89: Scenario multipliers (OpEx & build) | B89: Value | C89: Unit | D89: Note
A90: Low | B90: 0.8 | C90: × | D90: Applied to OpEx and build in TCO
A91: Base | B91: 1 | C91: ×
A92: High | B92: 1.3 | C92: ×
A94: Capitalization | B94: Value | C94: Unit | D94: Note
A95: Capitalization approved % | B95: 0 | C95: % | D95: CFO decision under Ind AS 38 / IAS 38 — default 0 until criteria evidenced

Sheet WorkPackages
A1: Work packages — hours are BLUE inputs (from scope_register.json); rate via VLOOKUP on Assumptions; cost = hours × rate
A3: WP | B3: Name | C3: Release | D3: Owner role | E3: Hours | F3: Rate (INR/h) | G3: Cost (INR) | H3: Category | I3: Dependencies | J3: Calendar stage
A4: WP-01 | B4: Discovery, source audit, requirement freeze | C4: R0 | D4: Solution architect | E4: 160 | F4: =VLOOKUP(D4,Assumptions!$A$5:$B$16,2,FALSE()) -> 3500 | G4: =E4*F4 -> 560000 | H4: Discovery | I4: — | J4: =IF(C4="ALL","Cross-cutting — all releases",INDEX(Assumptions!$A$26:$A$32,MATCH(C4&" —*",Assumptions!$A$26:$A$32,0))&" ("&INDEX(Assumptions!$B$26:$B$32,MATCH(C4&" —*",Assumptions!$A$26:$A$32,0))&" wk)") -> R0 — Read-only pilot & foundations (8 wk)
A5: WP-02 | B5: UX design system, atlas, accessibility baseline | C5: R0 | D5: Product designer | E5: 240 | F5: =VLOOKUP(D5,Assumptions!$A$5:$B$16,2,FALSE()) -> 2000 | G5: =E5*F5 -> 480000 | H5: Design | I5: WP-01 | J5: =IF(C5="ALL","Cross-cutting — all releases",INDEX(Assumptions!$A$26:$A$32,MATCH(C5&" —*",Assumptions!$A$26:$A$32,0))&" ("&INDEX(Assumptions!$B$26:$B$32,MATCH(C5&" —*",Assumptions!$A$26:$A$32,0))&" wk)") -> R0 — Read-only pilot & foundations (8 wk)
A6: WP-03 | B6: Platform foundation: FastAPI, Postgres, queue, auth, RBAC, audit log, observability | C6: R0 | D6: Backend lead | E6: 420 | F6: =VLOOKUP(D6,Assumptions!$A$5:$B$16,2,FALSE()) -> 3000 | G6: =E6*F6 -> 1260000 | H6: Backend | I6: WP-01 | J6: =IF(C6="ALL","Cross-cutting — all releases",INDEX(Assumptions!$A$26:$A$32,MATCH(C6&" —*",Assumptions!$A$26:$A$32,0))&" ("&INDEX(Assumptions!$B$26:$B$32,MATCH(C6&" —*",Assumptions!$A$26:$A$32,0))&" wk)") -> R0 — Read-only pilot & foundations (8 wk)
A7: WP-04 | B7: Workspace & entity model: legal entities, brands, stores, markets, currencies, timezones, periods | C7: R0 | D7: Backend | E7: 220 | F7: =VLOOKUP(D7,Assumptions!$A$5:$B$16,2,FALSE()) -> 2400 | G7: =E7*F7 -> 528000 | H7: Backend | I7: WP-03 | J7: =IF(C7="ALL","Cross-cutting — all releases",INDEX(Assumptions!$A$26:$A$32,MATCH(C7&" —*",Assumptions!$A$26:$A$32,0))&" ("&INDEX(Assumptions!$B$26:$B$32,MATCH(C7&" —*",Assumptions!$A$26:$A$32,0))&" wk)") -> R0 — Read-only pilot & foundations (8 wk)
A8: WP-05 | B8: Amazon SP-API read connector: orders, finances, reports, settlements, inventory, inbound | C8: R0 | D8: Integration eng | E8: 480 | F8: =VLOOKUP(D8,Assumptions!$A$5:$B$16,2,FALSE()) -> 2600 | G8: =E8*F8 -> 1248000 | H8: Connector core | I8: WP-03, SP-API developer registration | J8: =IF(C8="ALL","Cross-cutting — all releases",INDEX(Assumptions!$A$26:$A$32,MATCH(C8&" —*",Assumptions!$A$26:$A$32,0))&" ("&INDEX(Assumptions!$B$26:$B$32,MATCH(C8&" —*",Assumptions!$A$26:$A$32,0))&" wk)") -> R0 — Read-only pilot & foundations (8 wk)
A9: WP-06 | B9: Raw ledger, event/revision model, idempotent ingestion, replay, reconciliation | C9: R0 | D9: Backend | E9: 320 | F9: =VLOOKUP(D9,Assumptions!$A$5:$B$16,2,FALSE()) -> 2400 | G9: =E9*F9 -> 768000 | H9: Backend | I9: WP-03, WP-05 | J9: =IF(C9="ALL","Cross-cutting — all releases",INDEX(Assumptions!$A$26:$A$32,MATCH(C9&" —*",Assumptions!$A$26:$A$32,0))&" ("&INDEX(Assumptions!$B$26:$B$32,MATCH(C9&" —*",Assumptions!$A$26:$A$32,0))&" wk)") -> R0 — Read-only pilot & foundations (8 wk)
A10: WP-07 | B10: Financial engine: fee taxonomy, COGS policies, allocations, FX, period close | C10: R1 | D10: Financial/data eng | E10: 520 | F10: =VLOOKUP(D10,Assumptions!$A$5:$B$16,2,FALSE()) -> 2600 | G10: =E10*F10 -> 1352000 | H10: Financial engine | I10: WP-06, WP-04 | J10: =IF(C10="ALL","Cross-cutting — all releases",INDEX(Assumptions!$A$26:$A$32,MATCH(C10&" —*",Assumptions!$A$26:$A$32,0))&" ("&INDEX(Assumptions!$B$26:$B$32,MATCH(C10&" —*",Assumptions!$A$26:$A$32,0))&" wk)") -> R1 — India-first unified profit core (14 wk)
A11: WP-08 | B11: Profit dashboards: tiles, chart, P&L, trends, map, comparisons, custom tiles | C11: R1 | D11: Frontend | E11: 480 | F11: =VLOOKUP(D11,Assumptions!$A$5:$B$16,2,FALSE()) -> 2200 | G11: =E11*F11 -> 1056000 | H11: Frontend | I11: WP-07, WP-02 | J11: =IF(C11="ALL","Cross-cutting — all releases",INDEX(Assumptions!$A$26:$A$32,MATCH(C11&" —*",Assumptions!$A$26:$A$32,0))&" ("&INDEX(Assumptions!$B$26:$B$32,MATCH(C11&" —*",Assumptions!$A$26:$A$32,0))&" wk)") -> R1 — India-first unified profit core (14 wk)
A12: WP-09 | B12: Products, COGS editor, landed-cost elements, imports/exports, sheets feed | C12: R1 | D12: Full-stack | E12: 360 | F12: =VLOOKUP(D12,Assumptions!$A$5:$B$16,2,FALSE()) -> 2400 | G12: =E12*F12 -> 864000 | H12: Frontend | I12: WP-07 | J12: =IF(C12="ALL","Cross-cutting — all releases",INDEX(Assumptions!$A$26:$A$32,MATCH(C12&" —*",Assumptions!$A$26:$A$32,0))&" ("&INDEX(Assumptions!$B$26:$B$32,MATCH(C12&" —*",Assumptions!$A$26:$A$32,0))&" wk)") -> R1 — India-first unified profit core (14 wk)
A13: WP-10 | B13: Expenses: indirect, variable/tag-based, recognition schedules, allocations | C13: R1 | D13: Full-stack | E13: 220 | F13: =VLOOKUP(D13,Assumptions!$A$5:$B$16,2,FALSE()) -> 2400 | G13: =E13*F13 -> 528000 | H13: Backend | I13: WP-07 | J13: =IF(C13="ALL","Cross-cutting — all releases",INDEX(Assumptions!$A$26:$A$32,MATCH(C13&" —*",Assumptions!$A$26:$A$32,0))&" ("&INDEX(Assumptions!$B$26:$B$32,MATCH(C13&" —*",Assumptions!$A$26:$A$32,0))&" wk)") -> R1 — India-first unified profit core (14 wk)
A14: WP-11 | B14: Reports & exports: grains, CSV/XLSX, scheduling, Claude-ready bundles | C14: R1 | D14: Backend | E14: 260 | F14: =VLOOKUP(D14,Assumptions!$A$5:$B$16,2,FALSE()) -> 2400 | G14: =E14*F14 -> 624000 | H14: Backend | I14: WP-07, WP-08 | J14: =IF(C14="ALL","Cross-cutting — all releases",INDEX(Assumptions!$A$26:$A$32,MATCH(C14&" —*",Assumptions!$A$26:$A$32,0))&" ("&INDEX(Assumptions!$B$26:$B$32,MATCH(C14&" —*",Assumptions!$A$26:$A$32,0))&" wk)") -> R1 — India-first unified profit core (14 wk)
A15: WP-12 | B15: Shopify connector: Admin GraphQL bulk, webhooks, Payments payouts, protected data | C15: R1 | D15: Integration eng | E15: 400 | F15: =VLOOKUP(D15,Assumptions!$A$5:$B$16,2,FALSE()) -> 2600 | G15: =E15*F15 -> 1040000 | H15: Connector core | I15: WP-06, Shopify read_all_orders approval | J15: =IF(C15="ALL","Cross-cutting — all releases",INDEX(Assumptions!$A$26:$A$32,MATCH(C15&" —*",Assumptions!$A$26:$A$32,0))&" ("&INDEX(Assumptions!$B$26:$B$32,MATCH(C15&" —*",Assumptions!$A$26:$A$32,0))&" wk)") -> R1 — India-first unified profit core (14 wk)
... A39: WP-39 | B39: Operations connectors: ShipStation, Flexport/SFN, Veeqo, CJ Dropshipping (read-only) | C39: R5 | D39: Integration eng | E39: 160 | F39: =VLOOKUP(D39,Assumptions!$A$5:$B$16,2,FALSE()) -> 2600 | G39: =E39*F39 -> 416000 | H39: Connector extended | I39: WP-06, WP-13; per-connector access | J39: =IF(C39="ALL","Cross-cutting — all releases",INDEX(Assumptions!$A$26:$A$32,MATCH(C39&" —*",Assumptions!$A$26:$A$32,0))&" ("&INDEX(Assumptions!$B$26:$B$32,MATCH(C39&" —*",Assumptions!$A$26:$A$32,0))&" wk)") -> R5 — Extended operations connectors & clients (10 wk)
A40: TOTAL | E40: =SUM(E4:E39) -> 11180 | G40: =SUM(G4:G39) -> 27604000 | I40: =IF(E40=11180,"OK — matches register 11,180 h","CHECK vs register 11,180 h") -> OK — matches register 11,180 h
A42: Category list (used by other sheets): Discovery, Design, Backend, Frontend, Financial engine, Connector core, Connector extended, Automation, QA-security, DevOps, Migration, Training, Leadership
A43: Note: 'Training' category has no WP (training is a one-time non-labour allowance on Assumptions); WP-29 covers migration + documentation labour. Categories and dependencies are planning classifications held in build_cost_model.py (not in the register).

Sheet Build_Summary
A1: Build summary — by release, initial bounded release vs full parity, by category
A2: All INR. Contingency = labour × contingency %.
A4: Release | B4: Hours | C4: Labour cost | D4: Contingency | E4: Total incl. contingency | F4: Note
A5: R0 — Read-only pilot & foundations | B5: =SUMIFS(WorkPackages!$E$4:$E$39,WorkPackages!$C$4:$C$39,"R0") -> 1840 | C5: =SUMIFS(WorkPackages!$G$4:$G$39,WorkPackages!$C$4:$C$39,"R0") -> 4844000 | D5: =C5*Assumptions!$B$19 -> 968800 | E5: =C5+D5 -> 5812800 | F5: Workspace, entities, connectors read-only, raw ledger, 90-day backfill, no operational wri
A6: R1 — India-first unified profit core | B6: =SUMIFS(WorkPackages!$E$4:$E$39,WorkPackages!$C$4:$C$39,"R1") -> 4200 | C6: =SUMIFS(WorkPackages!$G$4:$G$39,WorkPackages!$C$4:$C$39,"R1") -> 10376000 | D6: =C6*Assumptions!$B$19 -> 2075200 | E6: =C6+D6 -> 12451200 | F6: One dashboard for Amazon.in + Shopify India + manual B2B: Sellerboard-compatible P&L, COGS
A7: R2 — All markets & marketplaces | B7: =SUMIFS(WorkPackages!$E$4:$E$39,WorkPackages!$C$4:$C$39,"R2") -> 1240 | C7: =SUMIFS(WorkPackages!$G$4:$G$39,WorkPackages!$C$4:$C$39,"R2") -> 3180000 | D7: =C7*Assumptions!$B$19 -> 636000 | E7: =C7+D7 -> 3816000 | F7: UK/US/FR/DE entities and stores, every other Amazon marketplace (NA/EU/FE regions), Walmar
A8: R3 — Operations | B8: =SUMIFS(WorkPackages!$E$4:$E$39,WorkPackages!$C$4:$C$39,"R3") -> 1260 | C8: =SUMIFS(WorkPackages!$G$4:$G$39,WorkPackages!$C$4:$C$39,"R3") -> 3024000 | D8: =C8*Assumptions!$B$19 -> 604800 | E8: =C8+D8 -> 3628800 | F8: Inventory planner, POs, suppliers, FBA/WFS shipments, reimbursement candidates (Money Back
A9: R4 — Pricing automation (conditional) | B9: =SUMIFS(WorkPackages!$E$4:$E$39,WorkPackages!$C$4:$C$39,"R4") -> 300 | C9: =SUMIFS(WorkPackages!$G$4:$G$39,WorkPackages!$C$4:$C$39,"R4") -> 720000 | D9: =C9*Assumptions!$B$19 -> 144000 | E9: =C9+D9 -> 864000 | F9: Repricer contract (simulation-first; writes only after approval, maker-checker, canary, ki
A10: R5 — Extended operations connectors & clients | B10: =SUMIFS(WorkPackages!$E$4:$E$39,WorkPackages!$C$4:$C$39,"R5") -> 740 | C10: =SUMIFS(WorkPackages!$G$4:$G$39,WorkPackages!$C$4:$C$39,"R5") -> 1764000 | D10: =C10*Assumptions!$B$19 -> 352800 | E10: =C10+D10 -> 2116800 | F10: ShipStation/Flexport/SFN/Veeqo/CJ connectors, PWA extras, browser extension, QuickBooks/Ta
A11: ALL | B11: =SUMIFS(WorkPackages!$E$4:$E$39,WorkPackages!$C$4:$C$39,"ALL") -> 1600 | C11: =SUMIFS(WorkPackages!$G$4:$G$39,WorkPackages!$C$4:$C$39,"ALL") -> 3696000 | D11: =C11*Assumptions!$B$19 -> 739200 | E11: =C11+D11 -> 4435200 | F11: Cross-cutting WPs (QA, DevOps, migration, leadership)
A12: TOTAL — Full approved parity (all WPs) | B12: =SUM(B5:B11) -> 11180 | C12: =SUM(C5:C11) -> 27604000 | D12: =SUM(D5:D11) -> 5520800 | E12: =SUM(E5:E11) -> 33124800
A14: Initial bounded release (R0 + R1 + pro-rata share of ALL WPs by hours)
A15: Pro-rata factor = (hours R0 + hours R1) ÷ (hours R0..R5, excluding ALL) | B15: =IF(SUM(B5:B10)=0,0,(B5+B6)/SUM(B5:B10)) -> 0.63048017
A16: Component | B16: Hours | C16: Labour cost | D16: Contingency | E16: Total incl. contingency | F16: Formula
A17: R0 + R1 direct | B17: =B5+B6 -> 6040 | C17: =C5+C6 -> 15220000 | D17: =D5+D6 -> 3044000 | E17: =E5+E6 -> 18264000 | F17: Sum of R0 and R1 rows
A18: Pro-rata share of ALL WPs | B18: =B11*$B$15 -> 1008.7683 | C18: =C11*$B$15 -> 2330254.7 | D18: =D11*$B$15 -> 466050.94 | E18: =E11*$B$15 -> 2796305.6 | F18: ALL row × pro-rata factor
A19: INITIAL BOUNDED RELEASE — total | B19: =B17+B18 -> 7048.7683 | C19: =C17+C18 -> 17550255 | D19: =D17+D18 -> 3510050.9 | E19: =E17+E18 -> 21060306
A20: FULL APPROVED PARITY — total | B20: =B12 -> 11180 | C20: =C12 -> 27604000 | D20: =D12 -> 5520800 | E20: =E12 -> 33124800
A21: Initial as % of full | C21: =IF(C20=0,0,C19/C20) -> 0.63578665
A23: By category
A24: Category | B24: Hours | C24: Labour cost | D24: Contingency | E24: Total incl. contingency | F24: Share of labour
A25: Discovery | B25: =SUMIFS(WorkPackages!$E$4:$E$39,WorkPackages!$H$4:$H$39,"Discovery") -> 160 | C25: =SUMIFS(WorkPackages!$G$4:$G$39,WorkPackages!$H$4:$H$39,"Discovery") -> 560000 | D25: =C25*Assumptions!$B$19 -> 112000 | E25: =C25+D25 -> 672000 | F25: =IF($C$12=0,0,C25/$C$12) -> 0.020286915
A26: Design | B26: =SUMIFS(WorkPackages!$E$4:$E$39,WorkPackages!$H$4:$H$39,"Design") -> 240 | C26: =SUMIFS(WorkPackages!$G$4:$G$39,WorkPackages!$H$4:$H$39,"Design") -> 480000 | D26: =C26*Assumptions!$B$19 -> 96000 | E26: =C26+D26 -> 576000 | F26: =IF($C$12=0,0,C26/$C$12) -> 0.017388784
A27: Backend | B27: =SUMIFS(WorkPackages!$E$4:$E$39,WorkPackages!$H$4:$H$39,"Backend") -> 2700 | C27: =SUMIFS(WorkPackages!$G$4:$G$39,WorkPackages!$H$4:$H$39,"Backend") -> 6732000 | D27: =C27*Assumptions!$B$19 -> 1346400 | E27: =C27+D27 -> 8078400 | F27: =IF($C$12=0,0,C27/$C$12) -> 0.2438777
A28: Frontend | B28: =SUMIFS(WorkPackages!$E$4:$E$39,WorkPackages!$H$4:$H$39,"Frontend") -> 1260 | C28: =SUMIFS(WorkPackages!$G$4:$G$39,WorkPackages!$H$4:$H$39,"Frontend") -> 2844000 | D28: =C28*Assumptions!$B$19 -> 568800 | E28: =C28+D28 -> 3412800 | F28: =IF($C$12=0,0,C28/$C$12) -> 0.10302855
A29: Financial engine | B29: =SUMIFS(WorkPackages!$E$4:$E$39,WorkPackages!$H$4:$H$39,"Financial engine") -> 1700 | C29: =SUMIFS(WorkPackages!$G$4:$G$39,WorkPackages!$H$4:$H$39,"Financial engine") -> 4376000 | D29: =C29*Assumptions!$B$19 -> 875200 | E29: =C29+D29 -> 5251200 | F29: =IF($C$12=0,0,C29/$C$12) -> 0.15852775
A30: Connector core | B30: =SUMIFS(WorkPackages!$E$4:$E$39,WorkPackages!$H$4:$H$39,"Connector core") -> 1580 | C30: =SUMIFS(WorkPackages!$G$4:$G$39,WorkPackages!$H$4:$H$39,"Connector core") -> 4108000 | D30: =C30*Assumptions!$B$19 -> 821600 | E30: =C30+D30 -> 4929600 | F30: =IF($C$12=0,0,C30/$C$12) -> 0.14881901
A31: Connector extended | B31: =SUMIFS(WorkPackages!$E$4:$E$39,WorkPackages!$H$4:$H$39,"Connector extended") -> 1120 | C31: =SUMIFS(WorkPackages!$G$4:$G$39,WorkPackages!$H$4:$H$39,"Connector extended") -> 2840000 | D31: =C31*Assumptions!$B$19 -> 568000 | E31: =C31+D31 -> 3408000 | F31: =IF($C$12=0,0,C31/$C$12) -> 0.10288364
A32: Automation | B32: =SUMIFS(WorkPackages!$E$4:$E$39,WorkPackages!$H$4:$H$39,"Automation") -> 820 | C32: =SUMIFS(WorkPackages!$G$4:$G$39,WorkPackages!$H$4:$H$39,"Automation") -> 1968000 | D32: =C32*Assumptions!$B$19 -> 393600 | E32: =C32+D32 -> 2361600 | F32: =IF($C$12=0,0,C32/$C$12) -> 0.071294015
A33: QA-security | B33: =SUMIFS(WorkPackages!$E$4:$E$39,WorkPackages!$H$4:$H$39,"QA-security") -> 640 | C33: =SUMIFS(WorkPackages!$G$4:$G$39,WorkPackages!$H$4:$H$39,"QA-security") -> 1152000 | D33: =C33*Assumptions!$B$19 -> 230400 | E33: =C33+D33 -> 1382400 | F33: =IF($C$12=0,0,C33/$C$12) -> 0.041733082
A34: DevOps | B34: =SUMIFS(WorkPackages!$E$4:$E$39,WorkPackages!$H$4:$H$39,"DevOps") -> 320 | C34: =SUMIFS(WorkPackages!$G$4:$G$39,WorkPackages!$H$4:$H$39,"DevOps") -> 768000 | D34: =C34*Assumptions!$B$19 -> 153600 | E34: =C34+D34 -> 921600 | F34: =IF($C$12=0,0,C34/$C$12) -> 0.027822055
A35: Migration | B35: =SUMIFS(WorkPackages!$E$4:$E$39,WorkPackages!$H$4:$H$39,"Migration") -> 240 | C35: =SUMIFS(WorkPackages!$G$4:$G$39,WorkPackages!$H$4:$H$39,"Migration") -> 576000 | D35: =C35*Assumptions!$B$19 -> 115200 | E35: =C35+D35 -> 691200 | F35: =IF($C$12=0,0,C35/$C$12) -> 0.020866541
A36: Training | B36: =SUMIFS(WorkPackages!$E$4:$E$39,WorkPackages!$H$4:$H$39,"Training") -> 0 | C36: =SUMIFS(WorkPackages!$G$4:$G$39,WorkPackages!$H$4:$H$39,"Training") -> 0 | D36: =C36*Assumptions!$B$19 -> 0 | E36: =C36+D36 -> 0 | F36: =IF($C$12=0,0,C36/$C$12) -> 0
A37: Leadership | B37: =SUMIFS(WorkPackages!$E$4:$E$39,WorkPackages!$H$4:$H$39,"Leadership") -> 400 | C37: =SUMIFS(WorkPackages!$G$4:$G$39,WorkPackages!$H$4:$H$39,"Leadership") -> 1200000 | D37: =C37*Assumptions!$B$19 -> 240000 | E37: =C37+D37 -> 1440000 | F37: =IF($C$12=0,0,C37/$C$12) -> 0.043471961
A38: TOTAL (check = full parity) | B38: =SUM(B25:B37) -> 11180 | C38: =SUM(C25:C37) -> 27604000 | D38: =SUM(D25:D37) -> 5520800 | E38: =SUM(E25:E37) -> 33124800 | F38: =IF(ABS(C38-C12)<1,"OK — reconciles","CHECK") -> OK — reconciles

Sheet Capacity_Schedule
A1: Capacity schedule — FTE by role per release = hours ÷ (nominal h/mo × productive factor) ÷ months in release
A2: Months = calendar weeks × 12/52 (weeks from scope_register.json via Assumptions). FTE > 1.0 flagged (needs more than one person of that role, or a longer calendar).
A4: Productive hours per FTE-month | B4: =Assumptions!$B$20*Assumptions!$B$21 -> 120
A6: Role | B6: R0 | C6: R1 | D6: R2 | E6: R3 | F6: R4 | G6: R5 | H6: ALL | I6: Flag | J6: R0 flag | K6: R1 flag | L6: R2 flag | M6: R3 flag | N6: R4 flag | O6: R5 flag | P6: ALL flag
A7: Calendar weeks | B7: =Assumptions!$B$26 -> 8 | C7: =Assumptions!$B$27 -> 14 | D7: =Assumptions!$B$28 -> 14 | E7: =Assumptions!$B$29 -> 10 | F7: =Assumptions!$B$30 -> 6 | G7: =Assumptions!$B$31 -> 10 | H7: =Assumptions!$B$32 -> 62
A8: Months | B8: =B7*12/52 -> 1.8461538 | C8: =C7*12/52 -> 3.2307692 | D8: =D7*12/52 -> 3.2307692 | E8: =E7*12/52 -> 2.3076923 | F8: =F7*12/52 -> 1.3846154 | G8: =G7*12/52 -> 2.3076923 | H8: =H7*12/52 -> 14.307692
A9: Solution architect | B9: =IF(B$8=0,0,SUMIFS(WorkPackages!$E$4:$E$39,WorkPackages!$D$4:$D$39,$A9,WorkPackages!$C$4:$C$39,"R0")/$B$4/B$8) -> 0.72222222 | C9: =IF(C$8=0,0,SUMIFS(WorkPackages!$E$4:$E$39,WorkPackages!$D$4:$D$39,$A9,WorkPackages!$C$4:$C$39,"R1")/$B$4/C$8) -> 0 | D9: =IF(D$8=0,0,SUMIFS(WorkPackages!$E$4:$E$39,WorkPackages!$D$4:$D$39,$A9,WorkPackages!$C$4:$C$39,"R2")/$B$4/D$8) -> 0 | E9: =IF(E$8=0,0,SUMIFS(WorkPackages!$E$4:$E$39,WorkPackages!$D$4:$D$39,$A9,WorkPackages!$C$4:$C$39,"R3")/$B$4/E$8) -> 0 | F9: =IF(F$8=0,0,SUMIFS(WorkPackages!$E$4:$E$39,WorkPackages!$D$4:$D$39,$A9,WorkPackages!$C$4:$C$39,"R4")/$B$4/F$8) -> 0 | G9: =IF(G$8=0,0,SUMIFS(WorkPackages!$E$4:$E$39,WorkPackages!$D$4:$D$39,$A9,WorkPackages!$C$4:$C$39,"R5")/$B$4/G$8) -> 0 | H9: =IF(H$8=0,0,SUMIFS(WorkPackages!$E$4:$E$39,WorkPackages!$D$4:$D$39,$A9,WorkPackages!$C$4:$C$39,"ALL")/$B$4/H$8) -> 0 | J9: =IF(B9>1,">1 FTE","") | K9: =IF(C9>1,">1 FTE","") | L9: =IF(D9>1,">1 FTE","") | M9: =IF(E9>1,">1 FTE","") | N9: =IF(F9>1,">1 FTE","") | O9: =IF(G9>1,">1 FTE","") | P9: =IF(H9>1,">1 FTE","")
A10: Backend lead | B10: =IF(B$8=0,0,SUMIFS(WorkPackages!$E$4:$E$39,WorkPackages!$D$4:$D$39,$A10,WorkPackages!$C$4:$C$39,"R0")/$B$4/B$8) -> 1.8958333 | C10: =IF(C$8=0,0,SUMIFS(WorkPackages!$E$4:$E$39,WorkPackages!$D$4:$D$39,$A10,WorkPackages!$C$4:$C$39,"R1")/$B$4/C$8) -> 0 | D10: =IF(D$8=0,0,SUMIFS(WorkPackages!$E$4:$E$39,WorkPackages!$D$4:$D$39,$A10,WorkPackages!$C$4:$C$39,"R2")/$B$4/D$8) -> 0 | E10: =IF(E$8=0,0,SUMIFS(WorkPackages!$E$4:$E$39,WorkPackages!$D$4:$D$39,$A10,WorkPackages!$C$4:$C$39,"R3")/$B$4/E$8) -> 0 | F10: =IF(F$8=0,0,SUMIFS(WorkPackages!$E$4:$E$39,WorkPackages!$D$4:$D$39,$A10,WorkPackages!$C$4:$C$39,"R4")/$B$4/F$8) -> 0 | G10: =IF(G$8=0,0,SUMIFS(WorkPackages!$E$4:$E$39,WorkPackages!$D$4:$D$39,$A10,WorkPackages!$C$4:$C$39,"R5")/$B$4/G$8) -> 0 | H10: =IF(H$8=0,0,SUMIFS(WorkPackages!$E$4:$E$39,WorkPackages!$D$4:$D$39,$A10,WorkPackages!$C$4:$C$39,"ALL")/$B$4/H$8) -> 0 | J10: =IF(B10>1,">1 FTE","") -> >1 FTE | K10: =IF(C10>1,">1 FTE","") | L10: =IF(D10>1,">1 FTE","") | M10: =IF(E10>1,">1 FTE","") | N10: =IF(F10>1,">1 FTE","") | O10: =IF(G10>1,">1 FTE","") | P10: =IF(H10>1,">1 FTE","")
A11: Backend | B11: =IF(B$8=0,0,SUMIFS(WorkPackages!$E$4:$E$39,WorkPackages!$D$4:$D$39,$A11,WorkPackages!$C$4:$C$39,"R0")/$B$4/B$8) -> 2.4375 | C11: =IF(C$8=0,0,SUMIFS(WorkPackages!$E$4:$E$39,WorkPackages!$D$4:$D$39,$A11,WorkPackages!$C$4:$C$39,"R1")/$B$4/C$8) -> 0.67063492 | D11: =IF(D$8=0,0,SUMIFS(WorkPackages!$E$4:$E$39,WorkPackages!$D$4:$D$39,$A11,WorkPackages!$C$4:$C$39,"R2")/$B$4/D$8) -> 0 | E11: =IF(E$8=0,0,SUMIFS(WorkPackages!$E$4:$E$39,WorkPackages!$D$4:$D$39,$A11,WorkPackages!$C$4:$C$39,"R3")/$B$4/E$8) -> 1.8777778 | F11: =IF(F$8=0,0,SUMIFS(WorkPackages!$E$4:$E$39,WorkPackages!$D$4:$D$39,$A11,WorkPackages!$C$4:$C$39,"R4")/$B$4/F$8) -> 0 | G11: =IF(G$8=0,0,SUMIFS(WorkPackages!$E$4:$E$39,WorkPackages!$D$4:$D$39,$A11,WorkPackages!$C$4:$C$39,"R5")/$B$4/G$8) -> 0.57777778 | H11: =IF(H$8=0,0,SUMIFS(WorkPackages!$E$4:$E$39,WorkPackages!$D$4:$D$39,$A11,WorkPackages!$C$4:$C$39,"ALL")/$B$4/H$8) -> 0 | J11: =IF(B11>1,">1 FTE","") -> >1 FTE | K11: =IF(C11>1,">1 FTE","") | L11: =IF(D11>1,">1 FTE","") | M11: =IF(E11>1,">1 FTE","") -> >1 FTE | N11: =IF(F11>1,">1 FTE","") | O11: =IF(G11>1,">1 FTE","") | P11: =IF(H11>1,">1 FTE","")
A12: Frontend | B12: =IF(B$8=0,0,SUMIFS(WorkPackages!$E$4:$E$39,WorkPackages!$D$4:$D$39,$A12,WorkPackages!$C$4:$C$39,"R0")/$B$4/B$8) -> 0 | C12: =IF(C$8=0,0,SUMIFS(WorkPackages!$E$4:$E$39,WorkPackages!$D$4:$D$39,$A12,WorkPackages!$C$4:$C$39,"R1")/$B$4/C$8) -> 1.7539683 | D12: =IF(D$8=0,0,SUMIFS(WorkPackages!$E$4:$E$39,WorkPackages!$D$4:$D$39,$A12,WorkPackages!$C$4:$C$39,"R2")/$B$4/D$8) -> 0 | E12: =IF(E$8=0,0,SUMIFS(WorkPackages!$E$4:$E$39,WorkPackages!$D$4:$D$39,$A12,WorkPackages!$C$4:$C$39,"R3")/$B$4/E$8) -> 0 | F12: =IF(F$8=0,0,SUMIFS(WorkPackages!$E$4:$E$39,WorkPackages!$D$4:$D$39,$A12,WorkPackages!$C$4:$C$39,"R4")/$B$4/F$8) -> 0 | G12: =IF(G$8=0,0,SUMIFS(WorkPackages!$E$4:$E$39,WorkPackages!$D$4:$D$39,$A12,WorkPackages!$C$4:$C$39,"R5")/$B$4/G$8) -> 0.79444444 | H12: =IF(H$8=0,0,SUMIFS(WorkPackages!$E$4:$E$39,WorkPackages!$D$4:$D$39,$A12,WorkPackages!$C$4:$C$39,"ALL")/$B$4/H$8) -> 0 | J12: =IF(B12>1,">1 FTE","") | K12: =IF(C12>1,">1 FTE","") -> >1 FTE | L12: =IF(D12>1,">1 FTE","") | M12: =IF(E12>1,">1 FTE","") | N12: =IF(F12>1,">1 FTE","") | O12: =IF(G12>1,">1 FTE","") | P12: =IF(H12>1,">1 FTE","")
A13: Full-stack | B13: =IF(B$8=0,0,SUMIFS(WorkPackages!$E$4:$E$39,WorkPackages!$D$4:$D$39,$A13,WorkPackages!$C$4:$C$39,"R0")/$B$4/B$8) -> 0 | C13: =IF(C$8=0,0,SUMIFS(WorkPackages!$E$4:$E$39,WorkPackages!$D$4:$D$39,$A13,WorkPackages!$C$4:$C$39,"R1")/$B$4/C$8) -> 2.8373016 | D13: =IF(D$8=0,0,SUMIFS(WorkPackages!$E$4:$E$39,WorkPackages!$D$4:$D$39,$A13,WorkPackages!$C$4:$C$39,"R2")/$B$4/D$8) -> 0 | E13: =IF(E$8=0,0,SUMIFS(WorkPackages!$E$4:$E$39,WorkPackages!$D$4:$D$39,$A13,WorkPackages!$C$4:$C$39,"R3")/$B$4/E$8) -> 2.6722222 | F13: =IF(F$8=0,0,SUMIFS(WorkPackages!$E$4:$E$39,WorkPackages!$D$4:$D$39,$A13,WorkPackages!$C$4:$C$39,"R4")/$B$4/F$8) -> 1.8055556 | G13: =IF(G$8=0,0,SUMIFS(WorkPackages!$E$4:$E$39,WorkPackages!$D$4:$D$39,$A13,WorkPackages!$C$4:$C$39,"R5")/$B$4/G$8) -> 0.72222222 | H13: =IF(H$8=0,0,SUMIFS(WorkPackages!$E$4:$E$39,WorkPackages!$D$4:$D$39,$A13,WorkPackages!$C$4:$C$39,"ALL")/$B$4/H$8) -> 0 | J13: =IF(B13>1,">1 FTE","") | K13: =IF(C13>1,">1 FTE","") -> >1 FTE | L13: =IF(D13>1,">1 FTE","") | M13: =IF(E13>1,">1 FTE","") -> >1 FTE | N13: =IF(F13>1,">1 FTE","") -> >1 FTE | O13: =IF(G13>1,">1 FTE","") | P13: =IF(H13>1,">1 FTE","")
A14: Integration eng | B14: =IF(B$8=0,0,SUMIFS(WorkPackages!$E$4:$E$39,WorkPackages!$D$4:$D$39,$A14,WorkPackages!$C$4:$C$39,"R0")/$B$4/B$8) -> 2.1666667 | C14: =IF(C$8=0,0,SUMIFS(WorkPackages!$E$4:$E$39,WorkPackages!$D$4:$D$39,$A14,WorkPackages!$C$4:$C$39,"R1")/$B$4/C$8) -> 2.218254 | D14: =IF(D$8=0,0,SUMIFS(WorkPackages!$E$4:$E$39,WorkPackages!$D$4:$D$39,$A14,WorkPackages!$C$4:$C$39,"R2")/$B$4/D$8) -> 2.1666667 | E14: =IF(E$8=0,0,SUMIFS(WorkPackages!$E$4:$E$39,WorkPackages!$D$4:$D$39,$A14,WorkPackages!$C$4:$C$39,"R3")/$B$4/E$8) -> 0 | F14: =IF(F$8=0,0,SUMIFS(WorkPackages!$E$4:$E$39,WorkPackages!$D$4:$D$39,$A14,WorkPackages!$C$4:$C$39,"R4")/$B$4/F$8) -> 0 | G14: =IF(G$8=0,0,SUMIFS(WorkPackages!$E$4:$E$39,WorkPackages!$D$4:$D$39,$A14,WorkPackages!$C$4:$C$39,"R5")/$B$4/G$8) -> 0.57777778 | H14: =IF(H$8=0,0,SUMIFS(WorkPackages!$E$4:$E$39,WorkPackages!$D$4:$D$39,$A14,WorkPackages!$C$4:$C$39,"ALL")/$B$4/H$8) -> 0 | J14: =IF(B14>1,">1 FTE","") -> >1 FTE | K14: =IF(C14>1,">1 FTE","") -> >1 FTE | L14: =IF(D14>1,">1 FTE","") -> >1 FTE | M14: =IF(E14>1,">1 FTE","") | N14: =IF(F14>1,">1 FTE","") | O14: =IF(G14>1,">1 FTE","") | P14: =IF(H14>1,">1 FTE","")
A15: Financial/data eng | B15: =IF(B$8=0,0,SUMIFS(WorkPackages!$E$4:$E$39,WorkPackages!$D$4:$D$39,$A15,WorkPackages!$C$4:$C$39,"R0")/$B$4/B$8) -> 0 | C15: =IF(C$8=0,0,SUMIFS(WorkPackages!$E$4:$E$39,WorkPackages!$D$4:$D$39,$A15,WorkPackages!$C$4:$C$39,"R1")/$B$4/C$8) -> 3.3531746 | D15: =IF(D$8=0,0,SUMIFS(WorkPackages!$E$4:$E$39,WorkPackages!$D$4:$D$39,$A15,WorkPackages!$C$4:$C$39,"R2")/$B$4/D$8) -> 0.46428571 | E15: =IF(E$8=0,0,SUMIFS(WorkPackages!$E$4:$E$39,WorkPackages!$D$4:$D$39,$A15,WorkPackages!$C$4:$C$39,"R3")/$B$4/E$8) -> 0 | F15: =IF(F$8=0,0,SUMIFS(WorkPackages!$E$4:$E$39,WorkPackages!$D$4:$D$39,$A15,WorkPackages!$C$4:$C$39,"R4")/$B$4/F$8) -> 0 | G15: =IF(G$8=0,0,SUMIFS(WorkPackages!$E$4:$E$39,WorkPackages!$D$4:$D$39,$A15,WorkPackages!$C$4:$C$39,"R5")/$B$4/G$8) -> 0 | H15: =IF(H$8=0,0,SUMIFS(WorkPackages!$E$4:$E$39,WorkPackages!$D$4:$D$39,$A15,WorkPackages!$C$4:$C$39,"ALL")/$B$4/H$8) -> 0 | J15: =IF(B15>1,">1 FTE","") | K15: =IF(C15>1,">1 FTE","") -> >1 FTE | L15: =IF(D15>1,">1 FTE","") | M15: =IF(E15>1,">1 FTE","") | N15: =IF(F15>1,">1 FTE","") | O15: =IF(G15>1,">1 FTE","") | P15: =IF(H15>1,">1 FTE","")
A16: Data eng | B16: =IF(B$8=0,0,SUMIFS(WorkPackages!$E$4:$E$39,WorkPackages!$D$4:$D$39,$A16,WorkPackages!$C$4:$C$39,"R0")/$B$4/B$8) -> 0 | C16: =IF(C$8=0,0,SUMIFS(WorkPackages!$E$4:$E$39,WorkPackages!$D$4:$D$39,$A16,WorkPackages!$C$4:$C$39,"R1")/$B$4/C$8) -> 0 | D16: =IF(D$8=0,0,SUMIFS(WorkPackages!$E$4:$E$39,WorkPackages!$D$4:$D$39,$A16,WorkPackages!$C$4:$C$39,"R2")/$B$4/D$8) -> 0.56746032 | E16: =IF(E$8=0,0,SUMIFS(WorkPackages!$E$4:$E$39,WorkPackages!$D$4:$D$39,$A16,WorkPackages!$C$4:$C$39,"R3")/$B$4/E$8) -> 0 | F16: =IF(F$8=0,0,SUMIFS(WorkPackages!$E$4:$E$39,WorkPackages!$D$4:$D$39,$A16,WorkPackages!$C$4:$C$39,"R4")/$B$4/F$8) -> 0 | G16: =IF(G$8=0,0,SUMIFS(WorkPackages!$E$4:$E$39,WorkPackages!$D$4:$D$39,$A16,WorkPackages!$C$4:$C$39,"R5")/$B$4/G$8) -> 0 | H16: =IF(H$8=0,0,SUMIFS(WorkPackages!$E$4:$E$39,WorkPackages!$D$4:$D$39,$A16,WorkPackages!$C$4:$C$39,"ALL")/$B$4/H$8) -> 0.13978495 | J16: =IF(B16>1,">1 FTE","") | K16: =IF(C16>1,">1 FTE","") | L16: =IF(D16>1,">1 FTE","") | M16: =IF(E16>1,">1 FTE","") | N16: =IF(F16>1,">1 FTE","") | O16: =IF(G16>1,">1 FTE","") | P16: =IF(H16>1,">1 FTE","")
A17: Product designer | B17: =IF(B$8=0,0,SUMIFS(WorkPackages!$E$4:$E$39,WorkPackages!$D$4:$D$39,$A17,WorkPackages!$C$4:$C$39,"R0")/$B$4/B$8) -> 1.0833333 | C17: =IF(C$8=0,0,SUMIFS(WorkPackages!$E$4:$E$39,WorkPackages!$D$4:$D$39,$A17,WorkPackages!$C$4:$C$39,"R1")/$B$4/C$8) -> 0 | D17: =IF(D$8=0,0,SUMIFS(WorkPackages!$E$4:$E$39,WorkPackages!$D$4:$D$39,$A17,WorkPackages!$C$4:$C$39,"R2")/$B$4/D$8) -> 0 | E17: =IF(E$8=0,0,SUMIFS(WorkPackages!$E$4:$E$39,WorkPackages!$D$4:$D$39,$A17,WorkPackages!$C$4:$C$39,"R3")/$B$4/E$8) -> 0 | F17: =IF(F$8=0,0,SUMIFS(WorkPackages!$E$4:$E$39,WorkPackages!$D$4:$D$39,$A17,WorkPackages!$C$4:$C$39,"R4")/$B$4/F$8) -> 0 | G17: =IF(G$8=0,0,SUMIFS(WorkPackages!$E$4:$E$39,WorkPackages!$D$4:$D$39,$A17,WorkPackages!$C$4:$C$39,"R5")/$B$4/G$8) -> 0 | H17: =IF(H$8=0,0,SUMIFS(WorkPackages!$E$4:$E$39,WorkPackages!$D$4:$D$39,$A17,WorkPackages!$C$4:$C$39,"ALL")/$B$4/H$8) -> 0 | J17: =IF(B17>1,">1 FTE","") -> >1 FTE | K17: =IF(C17>1,">1 FTE","") | L17: =IF(D17>1,">1 FTE","") | M17: =IF(E17>1,">1 FTE","") | N17: =IF(F17>1,">1 FTE","") | O17: =IF(G17>1,">1 FTE","") | P17: =IF(H17>1,">1 FTE","")
A18: QA/security | B18: =IF(B$8=0,0,SUMIFS(WorkPackages!$E$4:$E$39,WorkPackages!$D$4:$D$39,$A18,WorkPackages!$C$4:$C$39,"R0")/$B$4/B$8) -> 0 | C18: =IF(C$8=0,0,SUMIFS(WorkPackages!$E$4:$E$39,WorkPackages!$D$4:$D$39,$A18,WorkPackages!$C$4:$C$39,"R1")/$B$4/C$8) -> 0 | D18: =IF(D$8=0,0,SUMIFS(WorkPackages!$E$4:$E$39,WorkPackages!$D$4:$D$39,$A18,WorkPackages!$C$4:$C$39,"R2")/$B$4/D$8) -> 0 | E18: =IF(E$8=0,0,SUMIFS(WorkPackages!$E$4:$E$39,WorkPackages!$D$4:$D$39,$A18,WorkPackages!$C$4:$C$39,"R3")/$B$4/E$8) -> 0 | F18: =IF(F$8=0,0,SUMIFS(WorkPackages!$E$4:$E$39,WorkPackages!$D$4:$D$39,$A18,WorkPackages!$C$4:$C$39,"R4")/$B$4/F$8) -> 0 | G18: =IF(G$8=0,0,SUMIFS(WorkPackages!$E$4:$E$39,WorkPackages!$D$4:$D$39,$A18,WorkPackages!$C$4:$C$39,"R5")/$B$4/G$8) -> 0 | H18: =IF(H$8=0,0,SUMIFS(WorkPackages!$E$4:$E$39,WorkPackages!$D$4:$D$39,$A18,WorkPackages!$C$4:$C$39,"ALL")/$B$4/H$8) -> 0.37275986 | J18: =IF(B18>1,">1 FTE","") | K18: =IF(C18>1,">1 FTE","") | L18: =IF(D18>1,">1 FTE","") | M18: =IF(E18>1,">1 FTE","") | N18: =IF(F18>1,">1 FTE","") | O18: =IF(G18>1,">1 FTE","") | P18: =IF(H18>1,">1 FTE","")
A19: DevOps | B19: =IF(B$8=0,0,SUMIFS(WorkPackages!$E$4:$E$39,WorkPackages!$D$4:$D$39,$A19,WorkPackages!$C$4:$C$39,"R0")/$B$4/B$8) -> 0 | C19: =IF(C$8=0,0,SUMIFS(WorkPackages!$E$4:$E$39,WorkPackages!$D$4:$D$39,$A19,WorkPackages!$C$4:$C$39,"R1")/$B$4/C$8) -> 0 | D19: =IF(D$8=0,0,SUMIFS(WorkPackages!$E$4:$E$39,WorkPackages!$D$4:$D$39,$A19,WorkPackages!$C$4:$C$39,"R2")/$B$4/D$8) -> 0 | E19: =IF(E$8=0,0,SUMIFS(WorkPackages!$E$4:$E$39,WorkPackages!$D$4:$D$39,$A19,WorkPackages!$C$4:$C$39,"R3")/$B$4/E$8) -> 0 | F19: =IF(F$8=0,0,SUMIFS(WorkPackages!$E$4:$E$39,WorkPackages!$D$4:$D$39,$A19,WorkPackages!$C$4:$C$39,"R4")/$B$4/F$8) -> 0 | G19: =IF(G$8=0,0,SUMIFS(WorkPackages!$E$4:$E$39,WorkPackages!$D$4:$D$39,$A19,WorkPackages!$C$4:$C$39,"R5")/$B$4/G$8) -> 0 | H19: =IF(H$8=0,0,SUMIFS(WorkPackages!$E$4:$E$39,WorkPackages!$D$4:$D$39,$A19,WorkPackages!$C$4:$C$39,"ALL")/$B$4/H$8) -> 0.18637993 | J19: =IF(B19>1,">1 FTE","") | K19: =IF(C19>1,">1 FTE","") | L19: =IF(D19>1,">1 FTE","") | M19: =IF(E19>1,">1 FTE","") | N19: =IF(F19>1,">1 FTE","") | O19: =IF(G19>1,">1 FTE","") | P19: =IF(H19>1,">1 FTE","")
A20: Delivery lead | B20: =IF(B$8=0,0,SUMIFS(WorkPackages!$E$4:$E$39,WorkPackages!$D$4:$D$39,$A20,WorkPackages!$C$4:$C$39,"R0")/$B$4/B$8) -> 0 | C20: =IF(C$8=0,0,SUMIFS(WorkPackages!$E$4:$E$39,WorkPackages!$D$4:$D$39,$A20,WorkPackages!$C$4:$C$39,"R1")/$B$4/C$8) -> 0 | D20: =IF(D$8=0,0,SUMIFS(WorkPackages!$E$4:$E$39,WorkPackages!$D$4:$D$39,$A20,WorkPackages!$C$4:$C$39,"R2")/$B$4/D$8) -> 0 | E20: =IF(E$8=0,0,SUMIFS(WorkPackages!$E$4:$E$39,WorkPackages!$D$4:$D$39,$A20,WorkPackages!$C$4:$C$39,"R3")/$B$4/E$8) -> 0 | F20: =IF(F$8=0,0,SUMIFS(WorkPackages!$E$4:$E$39,WorkPackages!$D$4:$D$39,$A20,WorkPackages!$C$4:$C$39,"R4")/$B$4/F$8) -> 0 | G20: =IF(G$8=0,0,SUMIFS(WorkPackages!$E$4:$E$39,WorkPackages!$D$4:$D$39,$A20,WorkPackages!$C$4:$C$39,"R5")/$B$4/G$8) -> 0 | H20: =IF(H$8=0,0,SUMIFS(WorkPackages!$E$4:$E$39,WorkPackages!$D$4:$D$39,$A20,WorkPackages!$C$4:$C$39,"ALL")/$B$4/H$8) -> 0.23297491 | J20: =IF(B20>1,">1 FTE","") | K20: =IF(C20>1,">1 FTE","") | L20: =IF(D20>1,">1 FTE","") | M20: =IF(E20>1,">1 FTE","") | N20: =IF(F20>1,">1 FTE","") | O20: =IF(G20>1,">1 FTE","") | P20: =IF(H20>1,">1 FTE","")
A21: Total FTE (role-sum) | B21: =SUM(B9:B20) -> 8.3055556 | C21: =SUM(C9:C20) -> 10.833333 | D21: =SUM(D9:D20) -> 3.1984127 | E21: =SUM(E9:E20) -> 4.55 | F21: =SUM(F9:F20) -> 1.8055556 | G21: =SUM(G9:G20) -> 2.6722222 | H21: =SUM(H9:H20) -> 0.93189964
A23: Reading: a value of 1.4 for 'Integration eng' in R1 means the R1 calendar needs 1.4 integration engineers at 120 productive h/month, or the release stretches. ALL column spreads cross-cutting WPs across the full programme (sum of release weeks). v0.3: R1 is 14 weeks and carries WP-07..13, WP-31..35 and WP-37; R2 (14 weeks) carries WP-14, WP-23, WP-36, WP-38.

Sheet OpEx_Monthly
A1: Monthly operating cost — line items from Assumptions; low / base / high = scenario multipliers
A2: INR. Annual = monthly × 12.
A4: Line item | B4: Applies from release | C4: Monthly (base) | D4: Monthly low | E4: Monthly high | F4: Annual base | G4: Annual low | H4: Annual high | I4: Source
A5: Cloud — compute | B5: R0 | C5: =Assumptions!$B$35 -> 45000 | D5: =C5*Assumptions!$B$90 -> 36000 | E5: =C5*Assumptions!$B$92 -> 58500 | F5: =C5*12 -> 540000 | G5: =D5*12 -> 432000 | H5: =E5*12 -> 702000 | I5: Assumptions sheet
A6: Cloud — managed Postgres | B6: R0 | C6: =Assumptions!$B$36 -> 25000 | D6: =C6*Assumptions!$B$90 -> 20000 | E6: =C6*Assumptions!$B$92 -> 32500 | F6: =C6*12 -> 300000 | G6: =D6*12 -> 240000 | H6: =E6*12 -> 390000 | I6: Assumptions sheet
A7: Cloud — object storage | B7: R0 | C7: =Assumptions!$B$37 -> 8000 | D7: =C7*Assumptions!$B$90 -> 6400 | E7: =C7*Assumptions!$B$92 -> 10400 | F7: =C7*12 -> 96000 | G7: =D7*12 -> 76800 | H7: =E7*12 -> 124800 | I7: Assumptions sheet
A8: Cloud — jobs / queue | B8: R0 | C8: =Assumptions!$B$38 -> 10000 | D8: =C8*Assumptions!$B$90 -> 8000 | E8: =C8*Assumptions!$B$92 -> 13000 | F8: =C8*12 -> 120000 | G8: =D8*12 -> 96000 | H8: =E8*12 -> 156000 | I8: Assumptions sheet
A9: Cloud — egress | B9: R0 | C9: =Assumptions!$B$39 -> 5000 | D9: =C9*Assumptions!$B$90 -> 4000 | E9: =C9*Assumptions!$B$92 -> 6500 | F9: =C9*12 -> 60000 | G9: =D9*12 -> 48000 | H9: =E9*12 -> 78000 | I9: Assumptions sheet
A10: Cloud — observability | B10: R0 | C10: =Assumptions!$B$40 -> 12000 | D10: =C10*Assumptions!$B$90 -> 9600 | E10: =C10*Assumptions!$B$92 -> 15600 | F10: =C10*12 -> 144000 | G10: =D10*12 -> 115200 | H10: =E10*12 -> 187200 | I10: Assumptions sheet
A11: Cloud — backups / DR | B11: R0 | C11: =Assumptions!$B$41 -> 6000 | D11: =C11*Assumptions!$B$90 -> 4800 | E11: =C11*Assumptions!$B$92 -> 7800 | F11: =C11*12 -> 72000 | G11: =D11*12 -> 57600 | H11: =E11*12 -> 93600 | I11: Assumptions sheet
A12: Cloud — security / landing zone | B12: R0 | C12: =Assumptions!$B$42 -> 18000 | D12: =C12*Assumptions!$B$90 -> 14400 | E12: =C12*Assumptions!$B$92 -> 23400 | F12: =C12*12 -> 216000 | G12: =D12*12 -> 172800 | H12: =E12*12 -> 280800 | I12: Assumptions sheet — NEW v0.2 (handoff review C-28)
A13: Support / maintenance staff | B13: R1 | C13: =Assumptions!$B$48 -> 192000 | D13: =C13*Assumptions!$B$90 -> 153600 | E13: =C13*Assumptions!$B$92 -> 249600 | F13: =C13*12 -> 2304000 | G13: =D13*12 -> 1843200 | H13: =E13*12 -> 2995200 | I13: Assumptions sheet
A14: Provider / API upgrade allowance | B14: R0 | C14: =Assumptions!$B$49 -> 20000 | D14: =C14*Assumptions!$B$90 -> 16000 | E14: =C14*Assumptions!$B$92 -> 26000 | F14: =C14*12 -> 240000 | G14: =D14*12 -> 192000 | H14: =E14*12 -> 312000 | I14: Assumptions sheet
A15: Security review (annual ÷ 12) | B15: R0 | C15: =Assumptions!$B$50/12 -> 25000 | D15: =C15*Assumptions!$B$90 -> 20000 | E15: =C15*Assumptions!$B$92 -> 32500 | F15: =C15*12 -> 300000 | G15: =D15*12 -> 240000 | H15: =E15*12 -> 390000 | I15: Assumptions sheet
A16: Software / API — SP-API | B16: R0 | C16: =Assumptions!$B$55 -> 0 | D16: =C16*Assumptions!$B$90 -> 0 | E16: =C16*Assumptions!$B$92 -> 0 | F16: =C16*12 -> 0 | G16: =D16*12 -> 0 | H16: =E16*12 -> 0 | I16: Assumptions sheet
A17: Software / API — Ads API (spend read) | B17: R1 | C17: =Assumptions!$B$56 -> 0 | D17: =C17*Assumptions!$B$90 -> 0 | E17: =C17*Assumptions!$B$92 -> 0 | F17: =C17*12 -> 0 | G17: =D17*12 -> 0 | H17: =E17*12 -> 0 | I17: Assumptions sheet — v0.3: spend read from R1 (WP-37); no PPC analytics
A18: Software / API — Shopify custom app | B18: R1 | C18: =Assumptions!$B$57 -> 0 | D18: =C18*Assumptions!$B$90 -> 0 | E18: =C18*Assumptions!$B$92 -> 0 | F18: =C18*12 -> 0 | G18: =D18*12 -> 0 | H18: =E18*12 -> 0 | I18: Assumptions sheet — v0.2: R1 (WP-12 moved R2→R1)
A19: Software / API — other tools | B19: R0 | C19: =Assumptions!$B$58 -> 15000 | D19: =C19*Assumptions!$B$90 -> 12000 | E19: =C19*Assumptions!$B$92 -> 19500 | F19: =C19*12 -> 180000 | G19: =D19*12 -> 144000 | H19: =E19*12 -> 234000 | I19: Assumptions sheet
A20: Software / API — ChatGPT/Codex seats (build tool) | B20: R0 | C20: =Assumptions!$B$61 -> 25200 | D20: =C20*Assumptions!$B$90 -> 20160 | E20: =C20*Assumptions!$B$92 -> 32760 | F20: =C20*12 -> 302400 | G20: =D20*12 -> 241920 | H20: =E20*12 -> 393120 | I20: Assumptions sheet — NEW v0.3 (DC-16; review finding v0.3-13)
A21: Courier/3PL data handling | B21: R1 | C21: =Assumptions!$B$52 -> 0 | D21: =C21*Assumptions!$B$90 -> 0 | E21: =C21*Assumptions!$B$92 -> 0 | F21: =C21*12 -> 0 | G21: =D21*12 -> 0 | H21: =E21*12 -> 0 | I21: Assumptions sheet — NEW v0.2; ₹0 ASSUMPTION (CON-32 / WP-35)
A22: AI consumption (Anthropic) | B22: R5 | C22: =Assumptions!$B$75 -> 49560 | D22: =C22*Assumptions!$B$90 -> 39648 | E22: =C22*Assumptions!$B$92 -> 64428 | F22: =C22*12 -> 594720 | G22: =D22*12 -> 475776 | H22: =E22*12 -> 773136 | I22: Assumptions sheet
A23: Optional native / extension upkeep | B23: R5 | C23: =Assumptions!$B$51 -> 40000 | D23: =C23*Assumptions!$B$90 -> 32000 | E23: =C23*Assumptions!$B$92 -> 52000 | F23: =C23*12 -> 480000 | G23: =D23*12 -> 384000 | H23: =E23*12 -> 624000 | I23: Assumptions sheet
A24: TOTAL OpEx — full parity (all lines) | C24: =SUM(C5:C23) -> 495760 | D24: =SUM(D5:D23) -> 396608 | E24: =SUM(E5:E23) -> 644488 | F24: =SUM(F5:F23) -> 5949120 | G24: =SUM(G5:G23) -> 4759296 | H24: =SUM(H5:H23) -> 7733856
A25: TOTAL OpEx — initial release (lines applicable ≤ R1) | C25: =SUMIFS(C5:C23,$B$5:$B$23,"R0")+SUMIFS(C5:C23,$B$5:$B$23,"R1") -> 406200 | D25: =SUMIFS(D5:D23,$B$5:$B$23,"R0")+SUMIFS(D5:D23,$B$5:$B$23,"R1") -> 324960 | E25: =SUMIFS(E5:E23,$B$5:$B$23,"R0")+SUMIFS(E5:E23,$B$5:$B$23,"R1") -> 528060 | F25: =SUMIFS(F5:F23,$B$5:$B$23,"R0")+SUMIFS(F5:F23,$B$5:$B$23,"R1") -> 4874400 | G25: =SUMIFS(G5:G23,$B$5:$B$23,"R0")+SUMIFS(G5:G23,$B$5:$B$23,"R1") -> 3899520 | H25: =SUMIFS(H5:H23,$B$5:$B$23,"R0")+SUMIFS(H5:H23,$B$5:$B$23,"R1") -> 6336720 | I25: Excludes AI consumption and native/extension upkeep (start R5); includes Ads API spend read (₹0), Shopify app and Courier/3PL line (R1)
A26: of which cloud subtotal | C26: =SUM(C5:C12) -> 129000
A27: 'Applies from release' (blue) drives which lines count toward the initial-release (R0+R1) OpEx and phased Year-1 on the TCO sheet.

Sheet TCO
A1: Total cost of ownership — cash basis; amortization shown as separate memo line (NOT added)
A2: INR. Build = labour + contingency + one-time non-labour + training. Cash TCO includes the 20% contingency as committed budget; it is shown separately in Build_Summary. OpEx from OpEx_Monthly (initial-release horizons use only lines applicable ≤R1). Low/base/high = scenario multipliers on Assumptions.
A4: Inputs pulled
A5: Initial bounded release build (labour + contingency) | B5: =Build_Summary!$E$19 -> 21060306
A6: Full approved parity build (labour + contingency) | B6: =Build_Summary!$E$12 -> 33124800
A7: One-time non-labour + training | B7: =Assumptions!$B$78+Assumptions!$B$79+Assumptions!$B$80 -> 650000
A8: Monthly OpEx (base) — full parity | B8: =OpEx_Monthly!$C$24 -> 495760
A9: Monthly OpEx (base) — initial release (lines ≤R1) | B9: =OpEx_Monthly!$C$25 -> 406200
A10: Scenario multipliers → | B10: =Assumptions!$B$90 -> 0.8 | C10: =Assumptions!$B$91 -> 1 | D10: =Assumptions!$B$92 -> 1.3
A12: A. Initial bounded release (R0+R1 + pro-rata ALL) — all build cash in month 0; OpEx lines ≤R1 only
A13: Horizon | B13: Low | C13: Base | D13: High | E13: Formula
A14: 12-month cash TCO | B14: =(B$5+B$7)*B$10+B$9*12*B$10 -> 21267765 | C14: =(B$5+B$7)*C$10+B$9*12*C$10 -> 26584706 | D14: =(B$5+B$7)*D$10+B$9*12*D$10 -> 34560117 | E14: (build + one-time) × mult + monthly OpEx × 12 × mult
A15: 24-month cash TCO | B15: =(B$5+B$7)*B$10+B$9*24*B$10 -> 25167285 | C15: =(B$5+B$7)*C$10+B$9*24*C$10 -> 31459106 | D15: =(B$5+B$7)*D$10+B$9*24*D$10 -> 40896837 | E15: (build + one-time) × mult + monthly OpEx × 24 × mult
A16: 36-month cash TCO | B16: =(B$5+B$7)*B$10+B$9*36*B$10 -> 29066805 | C16: =(B$5+B$7)*C$10+B$9*36*C$10 -> 36333506 | D16: =(B$5+B$7)*D$10+B$9*36*D$10 -> 47233557 | E16: (build + one-time) × mult + monthly OpEx × 36 × mult
A18: B. Full approved parity — all build cash in month 0; full OpEx
A19: Horizon | B19: Low | C19: Base | D19: High | E19: Formula
A20: 12-month cash TCO | B20: =(B$6+B$7)*B$10+B$8*12*B$10 -> 31779136 | C20: =(B$6+B$7)*C$10+B$8*12*C$10 -> 39723920 | D20: =(B$6+B$7)*D$10+B$8*12*D$10 -> 51641096 | E20: (build + one-time) × mult + monthly OpEx × 12 × mult
A21: 24-month cash TCO | B21: =(B$6+B$7)*B$10+B$8*24*B$10 -> 36538432 | C21: =(B$6+B$7)*C$10+B$8*24*C$10 -> 45673040 | D21: =(B$6+B$7)*D$10+B$8*24*D$10 -> 59374952 | E21: (build + one-time) × mult + monthly OpEx × 24 × mult
A22: 36-month cash TCO | B22: =(B$6+B$7)*B$10+B$8*36*B$10 -> 41297728 | C22: =(B$6+B$7)*C$10+B$8*36*C$10 -> 51622160 | D22: =(B$6+B$7)*D$10+B$8*36*D$10 -> 67108808 | E22: (build + one-time) × mult + monthly OpEx × 36 × mult
A24: C. Phased full parity — R0–R1 in year 1, R2–R3 in year 2, R4–R5 in year 3 (ALL WPs pro-rata by hours per year)
A25: Year | B25: Build cash in year (base) | C25: OpEx in year (base) | D25: Cumulative cash TCO (base) | E25: Formula
A26: Year 1 (R0+R1) | B26: =Build_Summary!$E$5+Build_Summary!$E$6+Build_Summary!$E$11*IF(SUM(Build_Summary!$B$5:$B$10)=0,0,(Build_Summary!$B$5+Build_Summary!$B$6)/SUM(Build_Summary!$B$5:$B$10))+B$7 -> 21710306 | C26: =B$9*12 -> 4874400 | D26: =B26+C26 -> 26584706 | E26: release totals incl. contingency + ALL × hours share + one-time; initial-release OpEx (≤R1) × 12
A27: Year 2 (R2+R3) | B27: =Build_Summary!$E$7+Build_Summary!$E$8+Build_Summary!$E$11*IF(SUM(Build_Summary!$B$5:$B$10)=0,0,(Build_Summary!$B$7+Build_Summary!$B$8)/SUM(Build_Summary!$B$5:$B$10)) -> 8602211.3 | C27: =B$9*12 -> 4874400 | D27: =D26+B27+C27 -> 40061317 | E27: release totals incl. contingency + ALL × hours share; OpEx lines ≤R1 × 12 (R5-only lines not yet live)
A28: Year 3 (R4+R5) | B28: =Build_Summary!$E$9+Build_Summary!$E$10+Build_Summary!$E$11*IF(SUM(Build_Summary!$B$5:$B$10)=0,0,(Build_Summary!$B$9+Build_Summary!$B$10)/SUM(Build_Summary!$B$5:$B$10)) -> 3462283.1 | C28: =B$8*12 -> 5949120 | D28: =D27+B28+C28 -> 49472720 | E28: release totals incl. contingency + ALL × hours share; full OpEx × 12
A29: Check: phased build sum = full parity build + one-time (phased TCO < B because Years 1–2 OpEx use the ≤R1 subset; phasing is illustrative — calendar is 62 weeks if sequential) | B29: =SUM(B26:B28) -> 33774800 | E29: =IF(ABS(B29-(B6+B7))<1,"OK — reconciles","CHECK") -> OK — reconciles
A30: Phased 36-month cash TCO — low / base / high | B30: =D28*B$10 -> 39578176 | C30: =D28*C$10 -> 49472720 | D30: =D28*D$10 -> 64314536
A32: MEMO — amortization (NOT cash, NOT added to TCO above)
A33: Horizon | B33: Approved CapEx | C33: Cumulative amortization | D33: Net book value | E33: Note
A34: 12 months | B34: =Accounting_Boundary!$C$22 -> 0 | C34: =MIN(Accounting_Boundary!$C$31*12,B34) -> 0 | D34: =B34-C34 -> 0 | E34: Straight-line over Assumptions amortization years, on approved CapEx only (default 0)
A35: 24 months | B35: =Accounting_Boundary!$C$22 -> 0 | C35: =MIN(Accounting_Boundary!$C$31*24,B35) -> 0 | D35: =B35-C35 -> 0 | E35: Straight-line over Assumptions amortization years, on approved CapEx only (default 0)
A36: 36 months | B36: =Accounting_Boundary!$C$22 -> 0 | C36: =MIN(Accounting_Boundary!$C$31*36,B36) -> 0 | D36: =B36-C36 -> 0 | E36: Straight-line over Assumptions amortization years, on approved CapEx only (default 0)

Sheet Accounting_Boundary
A1: Accounting boundary — CapEx-candidate (development) vs expensed, by WP category
A2: Candidate-qualifying % is a judgement INPUT per category (blue). Actual capitalization requires CFO approval; default approved % = 0.
A4: Category | B4: Hours | C4: Labour cost | D4: Candidate-qualifying % | E4: Candidate-qualifying cost | F4: Expensed cost | G4: Rationale (planning judgement — not accounting advice)
A5: Discovery | B5: =SUMIFS(WorkPackages!$E$4:$E$39,WorkPackages!$H$4:$H$39,"Discovery") -> 160 | C5: =SUMIFS(WorkPackages!$G$4:$G$39,WorkPackages!$H$4:$H$39,"Discovery") -> 560000 | D5: 0 | E5: =C5*D5 -> 0 | F5: =C5-E5 -> 560000 | G5: Research phase — expensed (IAS 38.54)
A6: Design | B6: =SUMIFS(WorkPackages!$E$4:$E$39,WorkPackages!$H$4:$H$39,"Design") -> 240 | C6: =SUMIFS(WorkPackages!$G$4:$G$39,WorkPackages!$H$4:$H$39,"Design") -> 480000 | D6: 0.8 | E6: =C6*D6 -> 384000 | F6: =C6-E6 -> 96000 | G6: UX design of the application — development; 20% exploratory
A7: Backend | B7: =SUMIFS(WorkPackages!$E$4:$E$39,WorkPackages!$H$4:$H$39,"Backend") -> 2700 | C7: =SUMIFS(WorkPackages!$G$4:$G$39,WorkPackages!$H$4:$H$39,"Backend") -> 6732000 | D7: 0.9 | E7: =C7*D7 -> 6058800 | F7: =C7-E7 -> 673200 | G7: Development of the asset; 10% spikes / rework (incl. WP-31 B2B module)
A8: Frontend | B8: =SUMIFS(WorkPackages!$E$4:$E$39,WorkPackages!$H$4:$H$39,"Frontend") -> 1260 | C8: =SUMIFS(WorkPackages!$G$4:$G$39,WorkPackages!$H$4:$H$39,"Frontend") -> 2844000 | D8: 0.9 | E8: =C8*D8 -> 2559600 | F8: =C8-E8 -> 284400 | G8: Development (incl. WP-33 mobile-first PWA shell)
A9: Financial engine | B9: =SUMIFS(WorkPackages!$E$4:$E$39,WorkPackages!$H$4:$H$39,"Financial engine") -> 1700 | C9: =SUMIFS(WorkPackages!$G$4:$G$39,WorkPackages!$H$4:$H$39,"Financial engine") -> 4376000 | D9: 0.9 | E9: =C9*D9 -> 3938400 | F9: =C9-E9 -> 437600 | G9: Development (incl. WP-32, WP-34, WP-36)
A10: Connector core | B10: =SUMIFS(WorkPackages!$E$4:$E$39,WorkPackages!$H$4:$H$39,"Connector core") -> 1580 | C10: =SUMIFS(WorkPackages!$G$4:$G$39,WorkPackages!$H$4:$H$39,"Connector core") -> 4108000 | D10: 0.9 | E10: =C10*D10 -> 3697200 | F10: =C10-E10 -> 410800 | G10: Development (incl. WP-35 Shopify cost completeness)
A11: Connector extended | B11: =SUMIFS(WorkPackages!$E$4:$E$39,WorkPackages!$H$4:$H$39,"Connector extended") -> 1120 | C11: =SUMIFS(WorkPackages!$G$4:$G$39,WorkPackages!$H$4:$H$39,"Connector extended") -> 2840000 | D11: 0.9 | E11: =C11*D11 -> 2556000 | F11: =C11-E11 -> 284000 | G11: Development (R5)
A12: Automation | B12: =SUMIFS(WorkPackages!$E$4:$E$39,WorkPackages!$H$4:$H$39,"Automation") -> 820 | C12: =SUMIFS(WorkPackages!$G$4:$G$39,WorkPackages!$H$4:$H$39,"Automation") -> 1968000 | D12: 0.9 | E12: =C12*D12 -> 1771200 | F12: =C12-E12 -> 196800 | G12: Development
A13: QA-security | B13: =SUMIFS(WorkPackages!$E$4:$E$39,WorkPackages!$H$4:$H$39,"QA-security") -> 640 | C13: =SUMIFS(WorkPackages!$G$4:$G$39,WorkPackages!$H$4:$H$39,"QA-security") -> 1152000 | D13: 0.5 | E13: =C13*D13 -> 576000 | F13: =C13-E13 -> 576000 | G13: Testing during development qualifies; UAT support & security review share expensed
A14: DevOps | B14: =SUMIFS(WorkPackages!$E$4:$E$39,WorkPackages!$H$4:$H$39,"DevOps") -> 320 | C14: =SUMIFS(WorkPackages!$G$4:$G$39,WorkPackages!$H$4:$H$39,"DevOps") -> 768000 | D14: 0.6 | E14: =C14*D14 -> 460800 | F14: =C14-E14 -> 307200 | G14: Environment build qualifies; run/operate share expensed
A15: Migration | B15: =SUMIFS(WorkPackages!$E$4:$E$39,WorkPackages!$H$4:$H$39,"Migration") -> 240 | C15: =SUMIFS(WorkPackages!$G$4:$G$39,WorkPackages!$H$4:$H$39,"Migration") -> 576000 | D15: 0 | E15: =C15*D15 -> 0 | F15: =C15-E15 -> 576000 | G15: Data conversion & documentation — expensed
A16: Training | B16: =SUMIFS(WorkPackages!$E$4:$E$39,WorkPackages!$H$4:$H$39,"Training") -> 0 | C16: =SUMIFS(WorkPackages!$G$4:$G$39,WorkPackages!$H$4:$H$39,"Training") -> 0 | D16: 0 | E16: =C16*D16 -> 0 | F16: =C16-E16 -> 0 | G16: Training — expensed (IAS 38.69)
A17: Leadership | B17: =SUMIFS(WorkPackages!$E$4:$E$39,WorkPackages!$H$4:$H$39,"Leadership") -> 400 | C17: =SUMIFS(WorkPackages!$G$4:$G$39,WorkPackages!$H$4:$H$39,"Leadership") -> 1200000 | D17: 0.3 | E17: =C17*D17 -> 360000 | F17: =C17-E17 -> 840000 | G17: Directly attributable PM share; change control / approvals expensed
A18: TOTAL labour | B18: =SUM(B5:B17) -> 11180 | C18: =SUM(C5:C17) -> 27604000 | D18: =IF(C18=0,0,E18/C18) -> 0.81009999 | E18: =SUM(E5:E17) -> 22362000 | F18: =SUM(F5:F17) -> 5242000 | G18: =IF(ABS(C18-Build_Summary!$C$12)<1,"OK — reconciles to Build_Summary","CHECK") -> OK — reconciles to Build_Summary
A20: Resulting classification (full parity)
A21: Capitalization approved % | C21: =Assumptions!$B$95 -> 0 | G21: Set on Assumptions after CFO review; default 0
A22: CapEx (approved) = candidate-qualifying × approved % | C22: =E18*C21 -> 0
A23: Expense = total labour − CapEx approved | C23: =C18-C22 -> 27604000
A24: Contingency reserve (committed budget; classified when drawn) | C24: =Build_Summary!$D$12 -> 5520800
A25: One-time non-labour (laptops/licences) — expensed or PPE per policy | C25: =Assumptions!$B$78 -> 400000
A26: Training — expensed | C26: =Assumptions!$B$79 -> 250000
A28: Amortization (only on approved CapEx)
A29: Amortization years | C29: =Assumptions!$B$23 -> 3
A30: Annual straight-line amortization | C30: =IF(C29=0,0,C22/C29) -> 0
A31: Monthly amortization | C31: =C30/12 -> 0
A33: Ind AS 38 / IAS 38 (para 57) — development costs may be capitalized only when ALL six criteria are demonstrated:
A34: 1) technical feasibility of completing the asset; 2) intention to complete and use it; 3) ability to use it; 4) how it will generate probable future economic benefits;
A35: 5) availability of adequate technical, financial and other resources to complete; 6) ability to measure attributable expenditure reliably.
A36: Research-phase (discovery), training, data migration/conversion, and post-implementation maintenance are expensed. Percentages above are planning judgements for a CFO / auditor review, not accounting advice.
A37: Cash TCO on the TCO sheet is unaffected by this classification; amortization is shown there as a separate memo line.

Sheet Build_vs_Buy
A1: Build vs buy — existing Sellerboard spend vs in-house app OpEx; payback on benefit threshold
A2: Benefit default 0 → payback shows 'N/A (benefit unproven)'. Excluded from both sides: ad spend, stock, fulfilment, GST.
A4: Item | B4: Monthly (INR) | C4: Annual (INR) | D4: Note
A5: Sellerboard (sellerboard.com) = accounts × USD/mo × FX | B5: =Assumptions!$B$85*Assumptions!$B$84*Assumptions!$B$22 -> 9828 | C5: =B5*12 -> 117936 | D5: OBSERVED: $39/mo Business plan on sellerboard.com; 3 accounts
A6: Sellerboard (sellerboard.io) = Shopify stores × USD/mo × FX | B6: =Assumptions!$B$87*Assumptions!$B$86*Assumptions!$B$22 -> 3276 | C6: =B6*12 -> 39312 | D6: ASSUMPTION: sellerboard.io plan unknown → $39/mo assumed; 1 Shopify store
A7: Sellerboard spend — total | B7: =B5+B6 -> 13104 | C7: =B7*12 -> 157248
A8: In-house app OpEx (base) — full parity | B8: =OpEx_Monthly!$C$24 -> 495760 | C8: =B8*12 -> 5949120 | D8: From OpEx_Monthly
A9: Monthly OpEx delta (app − Sellerboard) | B9: =B8-B7 -> 482656 | C9: =B9*12 -> 5791872 | D9: Positive = app costs more to run than Sellerboard
A10: Sellerboard spend as % of app OpEx | B10: =IF(B8=0,0,B7/B8) -> 0.026432145
A12: Payback
A13: Monthly benefit threshold (INR) — from Assumptions | B13: =Assumptions!$B$83 -> 0 | D13: Default 0 = unproven. Enter only evidenced margin gains / savings.
A14: Net monthly benefit = benefit − OpEx delta | B14: =B13-B9 -> -482656
A15: Payback (months) — initial bounded release | B15: =IF(B13<=0,"N/A (benefit unproven)",IF(B14<=0,"N/A (no net monthly benefit)",(Build_Summary!$E$19+Assumptions!$B$78+Assumptions!$B$79)/B14)) -> N/A (benefit unproven) | D15: Formula: (build incl. contingency + one-time) ÷ net monthly benefit
A16: Payback (months) — full parity | B16: =IF(B13<=0,"N/A (benefit unproven)",IF(B14<=0,"N/A (no net monthly benefit)",(Build_Summary!$E$12+Assumptions!$B$78+Assumptions!$B$79)/B14)) -> N/A (benefit unproven) | D16: Formula: (build incl. contingency + one-time) ÷ net monthly benefit
A17: Monthly benefit needed for 36-month payback (full parity) | B17: =(Build_Summary!$E$12+Assumptions!$B$78+Assumptions!$B$79)/36+B9 -> 1420844.9 | D17: Reference: benefit that would be required, not a forecast
A19: Excluded costs on both sides: advertising spend, inventory/stock purchases, fulfilment & shipping fees, marketplace commissions, GST, office overhead.
A20: Sellerboard replacement is not cost-driven at these figures: the app's OpEx alone exceeds the combined sellerboard.com + sellerboard.io subscription many times over; the case rests on evidenced benefits (data ownership, India-first fee taxonomy, unified Amazon + Shopify + B2B view, automation with maker-checker) that this sheet treats as unproven until entered.

Sheet Sensitivity
A1: Sensitivity — effect on 36-month cash TCO (full parity, base scenario)
A2: Each row varies one driver from the base; all formulas reference TCO and OpEx sheets. Multipliers in column B are BLUE inputs.
A4: Base 36-month TCO (full parity, base) | B4: =TCO!$C$22 -> 51622160
A5: Labour incl. contingency (full parity) | B5: =Build_Summary!$E$12 -> 33124800
A6: Cloud monthly (base) | B6: =OpEx_Monthly!$C$26 -> 129000
A7: AI monthly (base) | B7: =OpEx_Monthly!$C$22 -> 49560
A9: Case | B9: Multiplier | C9: Δ 36-month TCO | D9: 36-month TCO | E9: Δ % | F9: Mechanism
A10: Hourly rates −20% | B10: 0.8 | C10: =$B$5*(B10-1) -> -6624960 | D10: =$B$4+C10 -> 44997200 | E10: =IF($B$4=0,0,C10/$B$4) -> -0.12833558 | F10: labour × (mult − 1)
A11: Hourly rates +20% | B11: 1.2 | C11: =$B$5*(B11-1) -> 6624960 | D11: =$B$4+C11 -> 58247120 | E11: =IF($B$4=0,0,C11/$B$4) -> 0.12833558 | F11: labour × (mult − 1)
A12: Hours −30% | B12: 0.7 | C12: =$B$5*(B12-1) -> -9937440 | D12: =$B$4+C12 -> 41684720 | E12: =IF($B$4=0,0,C12/$B$4) -> -0.19250337 | F12: labour × (mult − 1)
A13: Hours +30% | B13: 1.3 | C13: =$B$5*(B13-1) -> 9937440 | D13: =$B$4+C13 -> 61559600 | E13: =IF($B$4=0,0,C13/$B$4) -> 0.19250337 | F13: labour × (mult − 1)
A14: Cloud −40% | B14: 0.6 | C14: =$B$6*36*(B14-1) -> -1857600 | D14: =$B$4+C14 -> 49764560 | E14: =IF($B$4=0,0,C14/$B$4) -> -0.035984546 | F14: cloud monthly × 36 × (mult − 1)
A15: Cloud +40% | B15: 1.4 | C15: =$B$6*36*(B15-1) -> 1857600 | D15: =$B$4+C15 -> 53479760 | E15: =IF($B$4=0,0,C15/$B$4) -> 0.035984546 | F15: cloud monthly × 36 × (mult − 1)
A16: AI tokens ×0.5 | B16: 0.5 | C16: =$B$7*36*(B16-1) -> -892080 | D16: =$B$4+C16 -> 50730080 | E16: =IF($B$4=0,0,C16/$B$4) -> -0.017280951 | F16: AI monthly × 36 × (mult − 1)
A17: AI tokens ×3 | B17: 3 | C17: =$B$7*36*(B17-1) -> 3568320 | D17: =$B$4+C17 -> 55190480 | E17: =IF($B$4=0,0,C17/$B$4) -> 0.069123803 | F17: AI monthly × 36 × (mult − 1)
A18: Combined worst case (rates +20%, hours +30%, cloud +40%, AI ×3) | C18: =$B$5*(B11*B13-1)+$B$6*36*(B15-1)+$B$7*36*(B17-1) -> 23975808 | D18: =$B$4+C18 -> 75597968 | E18: =IF($B$4=0,0,C18/$B$4) -> 0.46444798 | F18: Multiplicative on labour (rate × hours multiplier cells); additive on OpEx drivers — references the multiplier cells above
A19: Note: rate and hours cases scale labour and its contingency together (contingency is a % of labour).

Sheet Traceability
A1: Traceability — WP → release → features (count from Features_Ref) → calculations / connectors
A2: Feature counts are COUNTIF formulas over Features_Ref (WP column). Calc/connector lists are text extracted from scope_register.json (union over the WP's features).
A3: WP | B3: Name | C3: Release | D3: Features (count) | E3: Hours | F3: Calculations (CALC ids) | G3: Connectors (CON ids) | H3: Cost (INR)
A4: WP-01 | B4: Discovery, source audit, requirement freeze | C4: =INDEX(WorkPackages!$C$4:$C$39,MATCH(A4,WorkPackages!$A$4:$A$39,0)) -> R0 | D4: =COUNTIF(Features_Ref!$H$4:$H$175,A4) -> 0 | E4: =INDEX(WorkPackages!$E$4:$E$39,MATCH(A4,WorkPackages!$A$4:$A$39,0)) -> 160 | F4: — | G4: — | H4: =INDEX(WorkPackages!$G$4:$G$39,MATCH(A4,WorkPackages!$A$4:$A$39,0)) -> 560000
A5: WP-02 | B5: UX design system, atlas, accessibility baseline | C5: =INDEX(WorkPackages!$C$4:$C$39,MATCH(A5,WorkPackages!$A$4:$A$39,0)) -> R0 | D5: =COUNTIF(Features_Ref!$H$4:$H$175,A5) -> 0 | E5: =INDEX(WorkPackages!$E$4:$E$39,MATCH(A5,WorkPackages!$A$4:$A$39,0)) -> 240 | F5: — | G5: — | H5: =INDEX(WorkPackages!$G$4:$G$39,MATCH(A5,WorkPackages!$A$4:$A$39,0)) -> 480000
A6: WP-03 | B6: Platform foundation: FastAPI, Postgres, queue, auth, RBAC, audit log, observability | C6: =INDEX(WorkPackages!$C$4:$C$39,MATCH(A6,WorkPackages!$A$4:$A$39,0)) -> R0 | D6: =COUNTIF(Features_Ref!$H$4:$H$175,A6) -> 4 | E6: =INDEX(WorkPackages!$E$4:$E$39,MATCH(A6,WorkPackages!$A$4:$A$39,0)) -> 420 | F6: — | G6: — | H6: =INDEX(WorkPackages!$G$4:$G$39,MATCH(A6,WorkPackages!$A$4:$A$39,0)) -> 1260000
A7: WP-04 | B7: Workspace & entity model: legal entities, brands, stores, markets, currencies, timezones, periods | C7: =INDEX(WorkPackages!$C$4:$C$39,MATCH(A7,WorkPackages!$A$4:$A$39,0)) -> R0 | D7: =COUNTIF(Features_Ref!$H$4:$H$175,A7) -> 3 | E7: =INDEX(WorkPackages!$E$4:$E$39,MATCH(A7,WorkPackages!$A$4:$A$39,0)) -> 220 | F7: CALC-026 | G7: — | H7: =INDEX(WorkPackages!$G$4:$G$39,MATCH(A7,WorkPackages!$A$4:$A$39,0)) -> 528000
A8: WP-05 | B8: Amazon SP-API read connector: orders, finances, reports, settlements, inventory, inbound | C8: =INDEX(WorkPackages!$C$4:$C$39,MATCH(A8,WorkPackages!$A$4:$A$39,0)) -> R0 | D8: =COUNTIF(Features_Ref!$H$4:$H$175,A8) -> 1 | E8: =INDEX(WorkPackages!$E$4:$E$39,MATCH(A8,WorkPackages!$A$4:$A$39,0)) -> 480 | F8: — | G8: CON-01 | H8: =INDEX(WorkPackages!$G$4:$G$39,MATCH(A8,WorkPackages!$A$4:$A$39,0)) -> 1248000
A9: WP-06 | B9: Raw ledger, event/revision model, idempotent ingestion, replay, reconciliation | C9: =INDEX(WorkPackages!$C$4:$C$39,MATCH(A9,WorkPackages!$A$4:$A$39,0)) -> R0 | D9: =COUNTIF(Features_Ref!$H$4:$H$175,A9) -> 2 | E9: =INDEX(WorkPackages!$E$4:$E$39,MATCH(A9,WorkPackages!$A$4:$A$39,0)) -> 320 | F9: — | G9: — | H9: =INDEX(WorkPackages!$G$4:$G$39,MATCH(A9,WorkPackages!$A$4:$A$39,0)) -> 768000
A10: WP-07 | B10: Financial engine: fee taxonomy, COGS policies, allocations, FX, period close | C10: =INDEX(WorkPackages!$C$4:$C$39,MATCH(A10,WorkPackages!$A$4:$A$39,0)) -> R1 | D10: =COUNTIF(Features_Ref!$H$4:$H$175,A10) -> 10 | E10: =INDEX(WorkPackages!$E$4:$E$39,MATCH(A10,WorkPackages!$A$4:$A$39,0)) -> 520 | F10: CALC-003, CALC-004, CALC-007, CALC-009, CALC-023, CALC-024, CALC-025, CALC-053, CALC-054, CALC-067, CALC-079, CALC-080, CALC-082, CALC-109 | G10: CON-01 | H10: =INDEX(WorkPackages!$G$4:$G$39,MATCH(A10,WorkPackages!$A$4:$A$39,0)) -> 1352000
A11: WP-08 | B11: Profit dashboards: tiles, chart, P&L, trends, map, comparisons, custom tiles | C11: =INDEX(WorkPackages!$C$4:$C$39,MATCH(A11,WorkPackages!$A$4:$A$39,0)) -> R1 | D11: =COUNTIF(Features_Ref!$H$4:$H$175,A11) -> 18 | E11: =INDEX(WorkPackages!$E$4:$E$39,MATCH(A11,WorkPackages!$A$4:$A$39,0)) -> 480 | F11: CALC-001, CALC-002, CALC-003, CALC-010, CALC-012, CALC-013, CALC-014, CALC-015, CALC-016, CALC-017, CALC-018, CALC-019, CALC-026, CALC-030, CALC-031, CALC-045, CALC-048, CALC-050, CALC-051, CALC-052, CALC-053, CALC-054, CALC-059, CALC-072, CALC-081, CALC-085, CALC-101, CALC-108, CALC-111 | G11: CON-01 | H11: =INDEX(WorkPackages!$G$4:$G$39,MATCH(A11,WorkPackages!$A$4:$A$39,0)) -> 1056000
A12: WP-09 | B12: Products, COGS editor, landed-cost elements, imports/exports, sheets feed | C12: =INDEX(WorkPackages!$C$4:$C$39,MATCH(A12,WorkPackages!$A$4:$A$39,0)) -> R1 | D12: =COUNTIF(Features_Ref!$H$4:$H$175,A12) -> 8 | E12: =INDEX(WorkPackages!$E$4:$E$39,MATCH(A12,WorkPackages!$A$4:$A$39,0)) -> 360 | F12: CALC-005, CALC-006, CALC-007, CALC-008, CALC-066, CALC-078, CALC-087 | G12: CON-23 | H12: =INDEX(WorkPackages!$G$4:$G$39,MATCH(A12,WorkPackages!$A$4:$A$39,0)) -> 864000
A13: WP-10 | B13: Expenses: indirect, variable/tag-based, recognition schedules, allocations | C13: =INDEX(WorkPackages!$C$4:$C$39,MATCH(A13,WorkPackages!$A$4:$A$39,0)) -> R1 | D13: =COUNTIF(Features_Ref!$H$4:$H$175,A13) -> 2 | E13: =INDEX(WorkPackages!$E$4:$E$39,MATCH(A13,WorkPackages!$A$4:$A$39,0)) -> 220 | F13: CALC-011, CALC-024, CALC-091 | G13: — | H13: =INDEX(WorkPackages!$G$4:$G$39,MATCH(A13,WorkPackages!$A$4:$A$39,0)) -> 528000
A14: WP-11 | B14: Reports & exports: grains, CSV/XLSX, scheduling, Claude-ready bundles | C14: =INDEX(WorkPackages!$C$4:$C$39,MATCH(A14,WorkPackages!$A$4:$A$39,0)) -> R1 | D14: =COUNTIF(Features_Ref!$H$4:$H$175,A14) -> 4 | E14: =INDEX(WorkPackages!$E$4:$E$39,MATCH(A14,WorkPackages!$A$4:$A$39,0)) -> 260 | F14: CALC-035, CALC-083 | G14: — | H14: =INDEX(WorkPackages!$G$4:$G$39,MATCH(A14,WorkPackages!$A$4:$A$39,0)) -> 624000
A15: WP-12 | B15: Shopify connector: Admin GraphQL bulk, webhooks, Payments payouts, protected data | C15: =INDEX(WorkPackages!$C$4:$C$39,MATCH(A15,WorkPackages!$A$4:$A$39,0)) -> R1 | D15: =COUNTIF(Features_Ref!$H$4:$H$175,A15) -> 2 | E15: =INDEX(WorkPackages!$E$4:$E$39,MATCH(A15,WorkPackages!$A$4:$A$39,0)) -> 400 | F15: — | G15: CON-05, CON-06 | H15: =INDEX(WorkPackages!$G$4:$G$39,MATCH(A15,WorkPackages!$A$4:$A$39,0)) -> 1040000
... A39: WP-39 | B39: Operations connectors: ShipStation, Flexport/SFN, Veeqo, CJ Dropshipping (read-only) | C39: =INDEX(WorkPackages!$C$4:$C$39,MATCH(A39,WorkPackages!$A$4:$A$39,0)) -> R5 | D39: =COUNTIF(Features_Ref!$H$4:$H$175,A39) -> 4 | E39: =INDEX(WorkPackages!$E$4:$E$39,MATCH(A39,WorkPackages!$A$4:$A$39,0)) -> 160 | F39: — | G39: CON-19, CON-20, CON-21, CON-22 | H39: =INDEX(WorkPackages!$G$4:$G$39,MATCH(A39,WorkPackages!$A$4:$A$39,0)) -> 416000
A40: TOTAL | D40: =SUM(D4:D39) -> 145 | E40: =SUM(E4:E39) -> 11180 | H40: =SUM(H4:H39) -> 27604000
A41: Features in register (COUNTA of Features_Ref) | D41: =COUNTA(Features_Ref!$A$4:$A$175) -> 172
A42: Features without WP mapping (NA + OMITTED v0.3) | D42: =COUNTIF(Features_Ref!$H$4:$H$175,"") -> 27
A43: Feature→WP links counted (= TOTAL above) | D43: =D40 -> 145
A44: Register feature count (scope_register.json v0.3) | D44: 172
A45: Check: COUNTA = register and links + unmapped = features | D45: =IF(AND(D41=D44,D43+D42=D41),"OK","CHECK") -> OK
A47: Features by release (COUNTIF over Features_Ref)
A48: Rel. | B48: Release | D48: IN | E48: COND. | F48: NA | G48: Total | H48: OMITTED
A49: R0 | B49: Read-only pilot & foundations | D49: =COUNTIFS(Features_Ref!$D$4:$D$175,$A49,Features_Ref!$E$4:$E$175,"IN") -> 10 | E49: =COUNTIFS(Features_Ref!$D$4:$D$175,$A49,Features_Ref!$E$4:$E$175,"CONDITIONAL") -> 0 | F49: =COUNTIFS(Features_Ref!$D$4:$D$175,$A49,Features_Ref!$E$4:$E$175,"NA") -> 0 | G49: =SUM(D49:F49)+H49 -> 10 | H49: =COUNTIFS(Features_Ref!$D$4:$D$175,$A49,Features_Ref!$E$4:$E$175,"OMITTED") -> 0
A50: R1 | B50: India-first unified profit core | D50: =COUNTIFS(Features_Ref!$D$4:$D$175,$A50,Features_Ref!$E$4:$E$175,"IN") -> 62 | E50: =COUNTIFS(Features_Ref!$D$4:$D$175,$A50,Features_Ref!$E$4:$E$175,"CONDITIONAL") -> 2 | F50: =COUNTIFS(Features_Ref!$D$4:$D$175,$A50,Features_Ref!$E$4:$E$175,"NA") -> 0 | G50: =SUM(D50:F50)+H50 -> 64 | H50: =COUNTIFS(Features_Ref!$D$4:$D$175,$A50,Features_Ref!$E$4:$E$175,"OMITTED") -> 0
A51: R2 | B51: All markets & marketplaces | D51: =COUNTIFS(Features_Ref!$D$4:$D$175,$A51,Features_Ref!$E$4:$E$175,"IN") -> 28 | E51: =COUNTIFS(Features_Ref!$D$4:$D$175,$A51,Features_Ref!$E$4:$E$175,"CONDITIONAL") -> 4 | F51: =COUNTIFS(Features_Ref!$D$4:$D$175,$A51,Features_Ref!$E$4:$E$175,"NA") -> 0 | G51: =SUM(D51:F51)+H51 -> 36 | H51: =COUNTIFS(Features_Ref!$D$4:$D$175,$A51,Features_Ref!$E$4:$E$175,"OMITTED") -> 4
A52: R3 | B52: Operations | D52: =COUNTIFS(Features_Ref!$D$4:$D$175,$A52,Features_Ref!$E$4:$E$175,"IN") -> 19 | E52: =COUNTIFS(Features_Ref!$D$4:$D$175,$A52,Features_Ref!$E$4:$E$175,"CONDITIONAL") -> 0 | F52: =COUNTIFS(Features_Ref!$D$4:$D$175,$A52,Features_Ref!$E$4:$E$175,"NA") -> 0 | G52: =SUM(D52:F52)+H52 -> 20 | H52: =COUNTIFS(Features_Ref!$D$4:$D$175,$A52,Features_Ref!$E$4:$E$175,"OMITTED") -> 1
A53: R4 | B53: Pricing automation (conditional) | D53: =COUNTIFS(Features_Ref!$D$4:$D$175,$A53,Features_Ref!$E$4:$E$175,"IN") -> 2 | E53: =COUNTIFS(Features_Ref!$D$4:$D$175,$A53,Features_Ref!$E$4:$E$175,"CONDITIONAL") -> 3 | F53: =COUNTIFS(Features_Ref!$D$4:$D$175,$A53,Features_Ref!$E$4:$E$175,"NA") -> 0 | G53: =SUM(D53:F53)+H53 -> 13 | H53: =COUNTIFS(Features_Ref!$D$4:$D$175,$A53,Features_Ref!$E$4:$E$175,"OMITTED") -> 8
A54: R5 | B54: Extended operations connectors & clients | D54: =COUNTIFS(Features_Ref!$D$4:$D$175,$A54,Features_Ref!$E$4:$E$175,"IN") -> 7 | E54: =COUNTIFS(Features_Ref!$D$4:$D$175,$A54,Features_Ref!$E$4:$E$175,"CONDITIONAL") -> 8 | F54: =COUNTIFS(Features_Ref!$D$4:$D$175,$A54,Features_Ref!$E$4:$E$175,"NA") -> 0 | G54: =SUM(D54:F54)+H54 -> 16 | H54: =COUNTIFS(Features_Ref!$D$4:$D$175,$A54,Features_Ref!$E$4:$E$175,"OMITTED") -> 1
A55: — | B55: No release (NA / not applicable) | D55: =COUNTIFS(Features_Ref!$D$4:$D$175,$A55,Features_Ref!$E$4:$E$175,"IN") -> 0 | E55: =COUNTIFS(Features_Ref!$D$4:$D$175,$A55,Features_Ref!$E$4:$E$175,"CONDITIONAL") -> 0 | F55: =COUNTIFS(Features_Ref!$D$4:$D$175,$A55,Features_Ref!$E$4:$E$175,"NA") -> 4 | G55: =SUM(D55:F55)+H55 -> 13 | H55: =COUNTIFS(Features_Ref!$D$4:$D$175,$A55,Features_Ref!$E$4:$E$175,"OMITTED") -> 9
A56: TOTAL | D56: =SUM(D49:D55) -> 128 | E56: =SUM(E49:E55) -> 17 | F56: =SUM(F49:F55) -> 4 | G56: =SUM(G49:G55) -> 172 | H56: =SUM(H49:H55) -> 23
A58: Note: each feature maps to at most one WP; OMITTED features (marketing, v0.3) carry no WP link and no cost; WP-01/02/27–30 carry no features directly (cross-cutting). Connector releases per register: CON-01:R0, CON-02:R1, CON-03:—, CON-04:—, CON-05:R1, CON-06:R1, CON-07:R2, CON-08:R1, CON-09:R1, CON-10:—, CON-11:R2, CON-12:—, CON-13:—, CON-14:—, CON-15:—, CON-16:R2, CON-17:R2, CON-18:R2, CON-19:R5, CON-20:R5, CON-21:R5, CON-22:R5, CON-23:R1, CON-24:—, CON-25:R4, CON-26:—, CON-27:R5, CON-28:R5, CON-29:R2, CON-32:R1, CON-33:R5. Stubs (no release): CON-30, CON-31. Omitted connectors show release '—'.

Sheet Features_Ref
A1: Feature extract from scope_register.json v0.3 (172 features; data for Traceability counts) — do not edit
A3: Feature | B3: Domain | C3: Name | D3: Release | E3: Disposition | F3: Calcs | G3: Connectors | H3: WP
A4: F-A01 | B4: A | C4: Login with MFA (authenticator app, e-mail), session policy | D4: R0 | E4: IN | H4: WP-03
A5: F-A02 | B5: A | C5: Multi-workspace / multi-account switcher | D5: R0 | E5: IN | H5: WP-04
A6: F-A03 | B6: A | C6: Legal entities, brands, stores, marketplaces, warehouses config | D6: R0 | E6: IN | H6: WP-04
A7: F-A04 | B7: A | C7: Currencies, timezones, target periods per store | D7: R0 | E7: IN | F7: CALC-026 | H7: WP-04
A8: F-A05 | B8: A | C8: Summary dashboard across accounts | D8: R2 | E8: IN | F8: CALC-013,CALC-051,CALC-101 | H8: WP-08
A9: F-A06 | B9: A | C9: User invitations & roles by function/product/market | D9: R0 | E9: IN | H9: WP-03
A10: F-A07 | B10: A | C10: Safe demo mode (synthetic data) | D10: R0 | E10: IN | H10: WP-03
A11: F-A08 | B11: A | C11: Data retention & lifecycle settings | D11: R0 | E11: IN | H11: WP-06
A12: F-A09 | B12: A | C12: Personalization: dark/light, remembered views, column pickers | D12: R1 | E12: IN | H12: WP-08
A13: F-A10 | B13: A | C13: Vendor SaaS billing / subscription | D13: — | E13: NA
A14: F-B01 | B14: B | C14: Profit tiles Today/Yesterday/MTD/Forecast/Last month with comparisons | D14: R1 | E14: IN | F14: CALC-002,CALC-013,CALC-045,CALC-108 | G14: CON-01 | H14: WP-08
A15: F-B02 | B15: B | C15: Tile 'More' P&L drilldown (expandable lines, fee breakdown) | D15: R1 | E15: IN | F15: CALC-001,CALC-003,CALC-010,CALC-012,CALC-015,CALC-019,CALC-050,CALC-051,CALC-052 | H15: WP-08
A16: F-B03 | B16: B | C16: Chart view (units/ads/refunds/net profit) with configuration | D16: R1 | E16: IN | H16: WP-08
A17: F-B04 | B17: B | C17: P&L table by day/month with heatmap and compare/YoY | D17: R1 | E17: IN | F17: CALC-013,CALC-050,CALC-051,CALC-108 | H17: WP-08
A18: F-B05 | B18: B | C18: Trends per product per metric with forecast column | D18: R1 | E18: IN | F18: CALC-030,CALC-031,CALC-108 | H18: WP-08
A19: F-B06 | B19: B | C19: Map / region view (sales, stock) | D19: R2 | E19: IN | F19: CALC-111 | H19: WP-08
A20: F-B07 | B20: B | C20: Products/Order-items tables with group-by, search, sort, column picker, export | D20: R1 | E20: IN | H20: WP-08
A21: F-B08 | B21: B | C21: Custom dashboard tiles (up to 8 metrics) | D21: R1 | E21: IN | H21: WP-08
A22: F-B09 | B22: B | C22: Targets, ASP, AOV, sessions/conversion, payout estimate | D22: R1 | E22: IN | F22: CALC-014,CALC-016,CALC-017,CALC-018,CALC-048,CALC-053,CALC-054 | H22: WP-08
A23: F-B10 | B23: B | C23: Amazon / Shopify / other-channel dashboard views | D23: R2 | E23: IN | H23: WP-08
A24: F-B11 | B24: B | C24: Dashboard currency switch | D24: R2 | E24: IN | F24: CALC-026,CALC-081 | H24: WP-08
A25: F-C01 | B25: C | C25: COGS policies: fixed, percentage, by period, batch, FIFO, weighted average | D25: R1 | E25: IN | F25: CALC-005,CALC-006,CALC-007,CALC-078 | H25: WP-09
A26: F-C02 | B26: C | C26: FIFO oversold policy (last batch / zero / fixed) + alert | D26: R1 | E26: IN | F26: CALC-007 | H26: WP-07
A27: F-C03 | B27: C | C27: Landed-cost elements per batch | D27: R1 | E27: IN | F27: CALC-008 | H27: WP-09
A28: F-C04 | B28: C | C28: SKU/ASIN/variant mapping, multi-channel COGS tab | D28: R1 | E28: IN | F28: CALC-066,CALC-087 | H28: WP-09
A29: F-C05 | B29: C | C29: Bundles / BOM | D29: R2 | E29: IN | F29: CALC-005 | H29: WP-09
A30: F-C06 | B30: C | C30: COGS import/export (CSV/XLSX), multi-product batch | D30: R1 | E30: IN | H30: WP-09
A31: F-C07 | B31: C | C31: Recurring COGS feed from Google Sheets / URL (daily) | D31: R1 | E31: IN | F31: CALC-087 | G31: CON-23 | H31: WP-09
A32: F-C08 | B32: C | C32: Missing/zero COGS detection and alert | D32: R1 | E32: IN | F32: CALC-043 | H32: WP-34
A33: F-C09 | B33: C | C33: Cost-change history, preview, closed-period effect | D33: R1 | E33: IN | F33: CALC-024 | H33: WP-07
A34: F-D01 | B34: D | C34: Marketplace fee taxonomy incl. India-specific (TDS, affordability, technology, closing) & unknown codes | D34: R1 | E34: IN | F34: CALC-003,CALC-067,CALC-109 | G34: CON-01 | H34: WP-07
A35: F-D02 | B35: D | C35: Refunds: partial, refund-without-return, unsellable, fee/tax reversals | D35: R1 | E35: IN | F35: CALC-004,CALC-009,CALC-053,CALC-054,CALC-082 | H35: WP-07
A36: F-D03 | B36: D | C36: Actual vs estimated shipping; ShipStation actuals | D36: R1 | E36: IN | F36: CALC-020 | G36: CON-32 | H36: WP-13
A37: F-D04 | B37: D | C37: Shipping profiles (zones/weight/value/units); highest-vs-sum mixed orders | D37: R1 | E37: IN | F37: CALC-020 | H37: WP-13
A38: F-D05 | B38: D | C38: Pick & pack per order/item, first-X-items rate | D38: R1 | E38: IN | F38: CALC-021 | H38: WP-13
A39: F-D06 | B39: D | C39: Gateway / POS / payment fees | D39: R1 | E39: IN | F39: CALC-022 | G39: CON-06 | H39: WP-13
A40: F-D07 | B40: D | C40: Indirect expenses: one-off/recurring/daily; multi-marketplace; tag/SKU | D40: R1 | E40: IN | F40: CALC-024 | H40: WP-10
A41: F-D08 | B41: D | C41: Variable / tag-based expenses with conditions and validity | D41: R1 | E41: IN | F41: CALC-011,CALC-091 | H41: WP-10
A42: F-D09 | B42: D | C42: Fee amortization (daily) for storage/inbound/removal etc. | D42: R1 | E42: IN | F42: CALC-024 | H42: WP-07
A43: F-D10 | B43: D | C43: Cross-market allocations & conservation | D43: R1 | E43: IN | F43: CALC-023 | H43: WP-07
A44: F-D11 | B44: D | C44: GST/TCS/VAT recoverability & marketplace-facilitator split | D44: R1 | E44: IN | F44: CALC-025 | H44: WP-07
A45: F-E01 | B45: E | C45: PPC dashboard portfolio→campaign→ad group→keyword→search term with profit & break-even ACOS | D45: R4 | E45: OMITTED | F45: CALC-028,CALC-029 | G45: CON-02
A46: F-E02 | B46: E | C46: Real ACOS / TACOS product-scoped on trends | D46: R1 | E46: IN | F46: CALC-030,CALC-031 | H46: WP-08
A47: F-E03 | B47: E | C47: Bid recommendations, harvesting, negatives, budget adjustments, isolation | D47: R4 | E47: OMITTED | F47: CALC-088,CALC-112 | G47: CON-26
A48: F-E04 | B48: E | C48: Automation: manual approval / autopilot; day parting (beta) | D48: R4 | E48: OMITTED | G48: CON-26
A49: F-E05 | B49: E | C49: Automation log completed/pending (repricer writes only) | D49: R4 | E49: IN | H49: WP-20
A50: F-E06 | B50: E | C50: External ads (Google/Meta/TikTok/Snap/Pinterest/Taboola) spend + UTM/session attribution | D50: R5 | E50: OMITTED | F50: CALC-032 | G50: CON-08..CON-14
A51: F-E07 | B51: E | C51: Amazon Attribution external traffic | D51: R2 | E51: OMITTED | F51: CALC-032 | G51: CON-04
A52: F-E08 | B52: E | C52: Search-term performance (Brand Analytics) | D52: R4 | E52: OMITTED | F52: CALC-074 | G52: CON-03
A53: F-E09 | B53: E | C53: Keyword research | D53: R4 | E53: OMITTED | G53: CON-03
A54: F-E10 | B54: E | C54: Product/ad mapping & organic vs paid split | D54: R4 | E54: OMITTED | F54: CALC-031,CALC-049
A55: F-E11 | B55: E | C55: First-party cookie / Shopify customerJourneySummary attribution | D55: R2 | E55: OMITTED | F55: CALC-032 | G55: CON-05
A56: F-F01 | B56: F | C56: LTV per buyer (sales, units, orders) 3/6/12/24 months, per product | D56: R2 | E56: IN | F56: CALC-033 | H56: WP-14
A57: F-F02 | B57: F | C57: Cohorts, retention, repeat rate, time-to-second purchase, CAC, payback with maturity flags | D57: R2 | E57: IN | F57: CALC-034,CALC-035,CALC-036 | H57: WP-14
A58: F-F03 | B58: F | C58: Repeat customers report (by brand) | D58: R2 | E58: IN | F58: CALC-035,CALC-083 | H58: WP-11
A59: F-F04 | B59: F | C59: Subscription contracts vs repeat orders (SnS count observed) | D59: R2 | E59: CONDITIONAL | G59: CON-29 | H59: WP-14
A60: F-G01 | B60: G | C60: Inventory by warehouse / fulfillment mode; reserved, saleable, damaged, prep, inbound, ordered | D60: R3 | E60: IN | F60: CALC-040 | G60: CON-01 | H60: WP-15
A61: F-G02 | B61: G | C61: Stock value & age, velocity, days of cover, safety stock, lead time | D61: R3 | E61: IN | F61: CALC-037,CALC-038 | H61: WP-15
A62: F-G03 | B62: G | C62: Reorder alerts / action-required with funds needed & profit at risk | D62: R3 | E62: IN | F62: CALC-039 | H62: WP-15
A63: F-G04 | B63: G | C63: Purchase orders (draft/ordered/shipped), suppliers (multi-currency), receiving, MOQ/carton | D63: R3 | E63: IN | F63: CALC-039 | H63: WP-15
A64: F-G05 | B64: G | C64: FBA / inbound shipment tracking, % received, discrepancies | D64: R3 | E64: IN | G64: CON-01 | H64: WP-15
A65: F-G06 | B65: G | C65: Prep-center stock auto-reduction on inbound | D65: R3 | E65: IN | F65: CALC-040 | H65: WP-15
A66: F-G07 | B66: G | C66: Stock history report & reconciliation, shrinkage | D66: R3 | E66: IN | F66: CALC-040 | H66: WP-15
A67: F-G08 | B67: G | C67: Reseller / sourcing workflow (mobile scan, FNSKU labels) | D67: R5 | E67: CONDITIONAL | G67: CON-01 | H67: WP-24
A68: F-H01 | B68: H | C68: Lost & damaged reimbursement candidates (estimate, report) | D68: R3 | E68: IN | F68: CALC-044 | G68: CON-01 | H68: WP-16
A69: F-H02 | B69: H | C69: Returns not received / refund-without-return candidates | D69: R3 | E69: IN | F69: CALC-044 | G69: CON-01 | H69: WP-16
A70: F-H03 | B70: H | C70: FBA fee-change (weight/dimension) candidates | D70: R3 | E70: IN | G70: CON-01 | H70: WP-16
A71: F-H04 | B71: H | C71: Claim tracker: eligibility, deadlines, policy version, evidence, appeals, realized credits | D71: R3 | E71: IN | F71: CALC-044 | H71: WP-16
A72: F-H05 | B72: H | C72: Review request campaigns: eligibility, targeting, schedules, dedup, per-order status | D72: R3 | E72: OMITTED | F72: CALC-042 | G72: CON-24
A73: F-H06 | B73: H | C73: Alerts: listing/Buy Box/seller count/fee/feedback/stock/ad-spend missing or spike/inbound; priorities; routing; resolution (no PPC recommendation alerts) | D73: R3 | E73: IN | F73: CALC-043 | H73: WP-17
A74: F-H07 | B74: H | C74: Alert notification channels (in-app, e-mail, per-recipient) & escalation | D74: R3 | E74: IN | H74: WP-17
A75: F-H08 | B75: H | C75: Custom buyer follow-up e-mails via Buyer-Seller Messaging | D75: — | E75: NA
A76: F-H09 | B76: H | C76: Alert notification channel in Seller Central | D76: — | E76: NA
A77: F-I01 | B77: I | C77: Repricer strategy profiles (max profit/sales/liquidation), min/max by ROI/margin/COGS+%, floor, overrides | D77: R4 | E77: CONDITIONAL | F77: CALC-041 | G77: CON-25 | H77: WP-22
A78: F-I02 | B78: I | C78: Guardrails: marketplace bounds, ±% caps, stale-data stop, kill switch, simulation, approval | D78: R4 | E78: CONDITIONAL | F78: CALC-041,CALC-075 | H78: WP-20
A79: F-I03 | B79: I | C79: Price history, Buy Box observations, change log, provider-result audit | D79: R4 | E79: IN | G79: CON-01 | H79: WP-22
A80: F-J01 | B80: J | C80: Walmart / WFS / Connect / SEM views, Walmart-only summary | D80: R2 | E80: IN | G80: CON-16 | H80: WP-23
A81: F-J02 | B81: J | C81: eBay dashboard, LTV, products, orders, expenses; order-level COGS import | D81: R2 | E81: IN | G81: CON-17 | H81: WP-23
A82: F-J03 | B82: J | C82: TikTok Shop (commerce) distinct from TikTok Ads | D82: R2 | E82: IN | G82: CON-18 | H82: WP-23
A83: F-J04 | B83: J | C83: Multichannel fulfillment order filtering & economic dedup (MCF/WFS) | D83: R2 | E83: IN | F83: CALC-047 | H83: WP-13
A84: F-J05 | B84: J | C84: Amazon→Shopify listing / MCF connector (historical claim) | D84: R5 | E84: CONDITIONAL | G84: CON-05 | H84: WP-23
A85: F-B12 | B85: B | C85: Unified dashboard: Amazon + Shopify + B2B in one tiles/chart/P&L/trends view with channel, account and entity filters | D85: R1 | E85: IN | F85: CALC-101,CALC-050,CALC-051 | G85: CON-01,CON-05 | H85: WP-32
A86: F-B13 | B86: B | C86: Sellerboard-compatible P&L mode (same line names, order and definitions) with contribution-margin toggle | D86: R1 | E86: IN | F86: CALC-050,CALC-051,CALC-052 | H86: WP-34
A87: F-B14 | B87: B | C87: Calculation lineage drawer and data freshness/completeness indicators | D87: R1 | E87: IN | H87: WP-34
A88: F-B15 | B88: B | C88: Targets and budget vs actual by channel/entity | D88: R2 | E88: IN | F88: CALC-107 | H88: WP-36
A89: F-B16 | B89: B | C89: Parallel-run reconciliation against Sellerboard exports during migration | D89: R1 | E89: IN | F89: CALC-051 | H89: WP-34
A90: F-B17 | B90: B | C90: SnS penetration and BSR snapshot | D90: R1 | E90: IN | F90: CALC-072,CALC-085 | G90: CON-01 | H90: WP-08
A91: F-C10 | B91: C | C91: COGS variants: tiered quantity cost, % of list/selling price, shared COGS master across channels | D91: R1 | E91: IN | F91: CALC-078,CALC-087 | H91: WP-09
A92: F-C11 | B92: C | C92: Closing a purchase order creates a cost batch with freight allocation | D92: R3 | E92: IN | F92: CALC-086 | H92: WP-15
A93: F-C12 | B93: C | C93: Grade & Resell COGS double-count guard | D93: R1 | E93: IN | F93: CALC-080 | H93: WP-07
A94: F-D12 | B94: D | C94: Shopify revenue composition: gross sales, discounts, shipping charged, refunds, tips, chargebacks, gift cards | D94: R1 | E94: IN | F94: CALC-076,CALC-052 | G94: CON-05 | H94: WP-13
A95: F-D13 | B95: D | C95: Payment fees per gateway (platform fee + gateway % + fixed; Auto actual) | D95: R1 | E95: IN | F95: CALC-022 | G95: CON-05,CON-06 | H95: WP-35
A96: F-D14 | B96: D | C96: Return shipping, return processing and country surcharge | D96: R1 | E96: IN | F96: CALC-077 | H96: WP-35
A97: F-D15 | B97: D | C97: Order inclusion rules (status/channel/tag) and COD/RTO cost handling | D97: R1 | E97: IN | F97: CALC-090,CALC-104 | G97: CON-05 | H97: WP-35
A98: F-D16 | B98: D | C98: Actual courier/3PL fulfilment cost import replacing profile estimates | D98: R1 | E98: CONDITIONAL | F98: CALC-105 | G98: CON-32 | H98: WP-35
A99: F-D17 | B99: D | C99: Advertising cost composition incl. flagged expenses and local GST on ads | D99: R1 | E99: IN | F99: CALC-079 | H99: WP-07
A100: F-D18 | B100: D | C100: Fee allocation: inbound by volume/weight; account-level fees by driver | D100: R1 | E100: IN | F100: CALC-067 | G100: CON-01 | H100: WP-07
A101: F-E12 | B101: E | C101: Dual attribution: platform-reported vs first/last-visit attributed, customer journey | D101: R2 | E101: OMITTED | F101: CALC-061,CALC-056 | G101: CON-05,CON-08,CON-09
...

Sheet Verification
A1: Verification — key totals (live links) — v0.3, cutoff 2026-10-10
A2: All values are formulas linking to the model; LibreOffice recalc via the xlsx skill's recalc.py must report 0 formula errors.
A4: Key total | B4: Value (INR unless stated) | C4: Source cell
A5: Initial bounded release build incl. contingency | B5: =Build_Summary!$E$19 -> 21060306 | C5: Build_Summary!E19
A6: Initial bounded release hours (R0+R1+pro-rata ALL) | B6: =Build_Summary!$B$19 -> 7048.7683 | C6: Build_Summary!B19
A7: Full approved parity build incl. contingency | B7: =Build_Summary!$E$12 -> 33124800 | C7: Build_Summary!E12
A8: Monthly OpEx base — full parity | B8: =OpEx_Monthly!$C$24 -> 495760 | C8: OpEx_Monthly!C24
A9: Monthly OpEx base — initial release (lines ≤R1) | B9: =OpEx_Monthly!$C$25 -> 406200 | C9: OpEx_Monthly!C25
A10: 36-month cash TCO — full parity, base | B10: =TCO!$C$22 -> 51622160 | C10: TCO!C22
A11: 36-month cash TCO — full parity, low | B11: =TCO!$B$22 -> 41297728 | C11: TCO!B22
A12: 36-month cash TCO — full parity, high | B12: =TCO!$D$22 -> 67108808 | C12: TCO!D22
A13: 36-month cash TCO — initial release, base | B13: =TCO!$C$16 -> 36333506 | C13: TCO!C16
A14: Build cost incl. contingency — R0 | B14: =Build_Summary!$E$5 -> 5812800 | C14: Build_Summary!E5
A15: Build cost incl. contingency — R1 | B15: =Build_Summary!$E$6 -> 12451200 | C15: Build_Summary!E6
A16: Build cost incl. contingency — R2 | B16: =Build_Summary!$E$7 -> 3816000 | C16: Build_Summary!E7
A17: Build cost incl. contingency — R3 | B17: =Build_Summary!$E$8 -> 3628800 | C17: Build_Summary!E8
A18: Build cost incl. contingency — R4 | B18: =Build_Summary!$E$9 -> 864000 | C18: Build_Summary!E9
A19: Build cost incl. contingency — R5 | B19: =Build_Summary!$E$10 -> 2116800 | C19: Build_Summary!E10
A20: Build cost incl. contingency — ALL | B20: =Build_Summary!$E$11 -> 4435200 | C20: Build_Summary!E11
A21: Total hours (all WPs) | B21: =WorkPackages!$E$40 -> 11180 | C21: WorkPackages!E40
A22: Features in register | B22: =Traceability!$D$41 -> 172 | C22: Traceability!D41
A23: Feature→WP links counted | B23: =Traceability!$D$40 -> 145 | C23: Traceability!D40
A24: Sellerboard spend (sellerboard.com + .io), monthly | B24: =Build_vs_Buy!$B$7 -> 13104 | C24: Build_vs_Buy!B7
A25: Category total reconciles to full parity | B25: =Build_Summary!$F$38 -> OK — reconciles | C25: Build_Summary!F38
A26: Phased TCO build reconciles | B26: =TCO!$E$29 -> OK — reconciles | C26: TCO!E29
A27: WorkPackages total vs register | B27: =WorkPackages!$I$40 -> OK — matches register 11,180 h | C27: WorkPackages!I40
A28: Traceability feature check | B28: =Traceability!$D$45 -> OK | C28: Traceability!D45
A30: Cash TCO includes the 20% contingency as committed budget; it is shown separately in Build_Summary. Regenerated by engineering/build_cost_model.py and verified by LibreOffice recalc (xlsx skill recalc.py) on 2026-10-10.

Sheet Change_v02_v03
A1: Change bridge — v0.2 vs v0.3 (both cutoff 2026-10-10)
A2: v0.2 column = BLUE hardcoded values from the v0.2 workbook (Verification sheet, LibreOffice-recalculated 2026-10-10, incl. the security/landing-zone OpEx line). v0.3 column = live formulas into this model. Assumption values (rates, contingency, OpEx lines, multipliers) are unchanged — differences are scope-driven (marketing omitted; all marketplaces in R2).
A4: A. Key totals
A5: Metric | B5: v0.2 | C5: v0.3 | D5: Δ (v0.3 − v0.2) | E5: Δ % | F5: Note
A6: Total hours (all WPs) | B6: 12000 | C6: =WorkPackages!$E$40 -> 11180 | D6: =C6-B6 -> -820 | E6: =IF(B6=0,0,D6/B6) -> -0.068333333 | F6: −1,220 h marketing (WP-18/19/21 retired, WP-14 −120, WP-20 −80, WP-23 −120) + 400 h new (WP-38, WP-39)
A7: Work packages (count) | B7: 37 | C7: =COUNTA(WorkPackages!$A$4:$A$39) -> 36 | D7: =C7-B7 -> -1 | E7: =IF(B7=0,0,D7/B7) -> -0.027027027 | F7: 3 retired, 2 added
A8: Programme calendar (weeks, R0–R5) | B8: 64 | C8: =Assumptions!$B$32 -> 62 | D8: =C8-B8 -> -2 | E8: =IF(B8=0,0,D8/B8) -> -0.03125 | F8: R2 10→14, R4 10→6, R5 12→10
A9: Initial bounded release — hours | B9: 6969.2308 | C9: =Build_Summary!$B$19 -> 7048.7683 | D9: =C9-B9 -> 79.537498 | E9: =IF(B9=0,0,D9/B9) -> 0.011412665 | F9: R0+R1+pro-rata ALL (pro-rata share changes because R2–R5 hours changed)
A10: Initial bounded release — INR incl. contingency | B10: 20839828 | C10: =Build_Summary!$E$19 -> 21060306 | D10: =C10-B10 -> 220477.94 | E10: =IF(B10=0,0,D10/B10) -> 0.010579643 | F10: R0/R1 scope unchanged
A11: Full approved parity — INR incl. contingency | B11: 35558400 | C11: =Build_Summary!$E$12 -> 33124800 | D11: =C11-B11 -> -2433600 | E11: =IF(B11=0,0,D11/B11) -> -0.068439525
A12: Monthly OpEx base — full parity | B12: 470560 | C12: =OpEx_Monthly!$C$24 -> 495760 | D12: =C12-B12 -> 25200 | E12: =IF(B12=0,0,D12/B12) -> 0.053553213 | F12: New ChatGPT/Codex seats line (12 × $25); Ads API line ₹0 (spend read)
A13: Monthly OpEx base — initial release (≤R1) | B13: 381000 | C13: =OpEx_Monthly!$C$25 -> 406200 | D13: =C13-B13 -> 25200 | E13: =IF(B13=0,0,D13/B13) -> 0.066141732 | F13: Includes ChatGPT/Codex seats from R0
A14: 36-month cash TCO — full parity, base | B14: 53148560 | C14: =TCO!$C$22 -> 51622160 | D14: =C14-B14 -> -1526400 | E14: =IF(B14=0,0,D14/B14) -> -0.028719499
A15: 36-month cash TCO — full parity, low | B15: 42518848 | C15: =TCO!$B$22 -> 41297728 | D15: =C15-B15 -> -1221120 | E15: =IF(B15=0,0,D15/B15) -> -0.028719499
A16: 36-month cash TCO — full parity, high | B16: 69093128 | C16: =TCO!$D$22 -> 67108808 | D16: =C16-B16 -> -1984320 | E16: =IF(B16=0,0,D16/B16) -> -0.028719499
A17: 36-month cash TCO — initial release, base | B17: 35205828 | C17: =TCO!$C$16 -> 36333506 | D17: =C17-B17 -> 1127677.9 | E17: =IF(B17=0,0,D17/B17) -> 0.032031002
A18: Build incl. contingency — R0 | B18: 5812800 | C18: =Build_Summary!$E$5 -> 5812800 | D18: =C18-B18 -> 0 | E18: =IF(B18=0,0,D18/B18) -> 0
A19: Build incl. contingency — R1 | B19: 12451200 | C19: =Build_Summary!$E$6 -> 12451200 | D19: =C19-B19 -> 0 | E19: =IF(B19=0,0,D19/B19) -> 0
A20: Build incl. contingency — R2 | B20: 1540800 | C20: =Build_Summary!$E$7 -> 3816000 | D20: =C20-B20 -> 2275200 | E20: =IF(B20=0,0,D20/B20) -> 1.4766355
A21: Build incl. contingency — R3 | B21: 4483200 | C21: =Build_Summary!$E$8 -> 3628800 | D21: =C21-B21 -> -854400 | E21: =IF(B21=0,0,D21/B21) -> -0.19057816
A22: Build incl. contingency — R4 | B22: 2971200 | C22: =Build_Summary!$E$9 -> 864000 | D22: =C22-B22 -> -2107200 | E22: =IF(B22=0,0,D22/B22) -> -0.7092084
A23: Build incl. contingency — R5 | B23: 3864000 | C23: =Build_Summary!$E$10 -> 2116800 | D23: =C23-B23 -> -1747200 | E23: =IF(B23=0,0,D23/B23) -> -0.45217391
A24: Build incl. contingency — ALL | B24: 4435200 | C24: =Build_Summary!$E$11 -> 4435200 | D24: =C24-B24 -> 0 | E24: =IF(B24=0,0,D24/B24) -> 0
A25: Features in register | B25: 165 | C25: =Traceability!$D$41 -> 172 | D25: =C25-B25 -> 7 | E25: =IF(B25=0,0,D25/B25) -> 0.042424242 | F25: 7 added (F-A11, F-A12, F-G11, F-J06…F-J09); 23 now OMITTED (kept for traceability, not built)
A27: B. Work packages that drove the change
A28: WP — name (v0.3, or v0.2 for retired) | B28: v0.2 hours | C28: v0.3 hours | D28: Δ hours | E28: Δ INR incl. cont. | F28: Driver
A29: (Retired WPs have 0 h in v0.3; their Δ INR uses the v0.2 owner-role rate from Assumptions.)
A30: WP-14 — LTV, repeat customers, cohorts & replenishment cycles (no ad attribution, no campaign analytics) | B30: 340 | C30: =INDEX(WorkPackages!$E$4:$E$39,MATCH("WP-14",WorkPackages!$A$4:$A$39,0)) -> 220 | D30: =C30-B30 -> -120 | E30: =D30*INDEX(WorkPackages!$F$4:$F$39,MATCH("WP-14",WorkPackages!$A$4:$A$39,0))*(1+Assumptions!$B$19) -> -345600 | F30: [R2→R2] Reduced 340→220 h: LTV, repeat customers, cohorts & replenishment kept; ad attribution, CAC payback by campaign and Amazon Attribution removed (marketing omitted)
A31: WP-18 — Review requests (Solicitations) — marketing, omitted v0.3 | B31: 200 | C31: 0 | D31: =C31-B31 -> -200 | E31: =D31*VLOOKUP("Integration eng",Assumptions!$A$5:$B$16,2,FALSE())*(1+Assumptions!$B$19) -> -624000 | F31: [R3→retired] RETIRED — review-request e-mails (Solicitations) are marketing; omitted by Owner 2026-10-10
A32: WP-19 — Amazon Ads campaign/PPC analytics — marketing, omitted v0.3 (ad spend read stays in WP-37) | B32: 380 | C32: 0 | D32: =C32-B32 -> -380 | E32: =D32*VLOOKUP("Integration eng",Assumptions!$A$5:$B$16,2,FALSE())*(1+Assumptions!$B$19) -> -1185600 | F32: [R4→retired] RETIRED — Amazon Ads campaign/PPC analytics omitted; ad SPEND read stays in WP-37 (R1)
A33: WP-20 — Automation safety framework for repricer writes: simulation, maker-checker, canary, kill switch, audit, replay | B33: 360 | C33: =INDEX(WorkPackages!$E$4:$E$39,MATCH("WP-20",WorkPackages!$A$4:$A$39,0)) -> 280 | D33: =C33-B33 -> -80 | E33: =D33*INDEX(WorkPackages!$F$4:$F$39,MATCH("WP-20",WorkPackages!$A$4:$A$39,0))*(1+Assumptions!$B$19) -> -230400 | F33: [R3→R3] Reduced 360→280 h: safety framework now serves repricer writes only (no PPC writes)
A34: WP-21 — PPC recommendations & bid/negative automation — marketing, omitted v0.3 | B34: 320 | C34: 0 | D34: =C34-B34 -> -320 | E34: =D34*VLOOKUP("Full-stack",Assumptions!$A$5:$B$16,2,FALSE())*(1+Assumptions!$B$19) -> -921600 | F34: [R4→retired] RETIRED — PPC recommendations, bid/budget/negative automation, day parting omitted
A35: WP-23 — Marketplace connectors: Walmart (Marketplace, WFS, Walmart Connect/SEM spend read), eBay, TikTok Shop — orders, fees, settlements, returns, inventory; compat P&L mapping | B35: 720 | C35: =INDEX(WorkPackages!$E$4:$E$39,MATCH("WP-23",WorkPackages!$A$4:$A$39,0)) -> 600 | D35: =C35-B35 -> -120 | E35: =D35*INDEX(WorkPackages!$F$4:$F$39,MATCH("WP-23",WorkPackages!$A$4:$A$39,0))*(1+Assumptions!$B$19) -> -374400 | F35: [R5→R2] Moved R5→R2 and re-scoped 720→600 h: Walmart (incl. WFS, Walmart Connect/SEM spend), eBay, TikTok Shop marketplaces only; external-ads & Klaviyo connectors removed; ops connectors split to WP-39
A36: WP-38 — All Amazon marketplaces: NA/EU/FE regions, marketplace master (currency, timezone, tax regime, fee codes), multi-region auth & rate limits, per-marketplace fixtures | B36: 0 | C36: =INDEX(WorkPackages!$E$4:$E$39,MATCH("WP-38",WorkPackages!$A$4:$A$39,0)) -> 240 | D36: =C36-B36 -> 240 | E36: =D36*INDEX(WorkPackages!$F$4:$F$39,MATCH("WP-38",WorkPackages!$A$4:$A$39,0))*(1+Assumptions!$B$19) -> 748800 | F36: [new→R2] NEW — all Amazon marketplaces (NA/EU/FE): marketplace master, tax regimes, multi-region auth (R2)
A37: WP-39 — Operations connectors: ShipStation, Flexport/SFN, Veeqo, CJ Dropshipping (read-only) | B37: 0 | C37: =INDEX(WorkPackages!$E$4:$E$39,MATCH("WP-39",WorkPackages!$A$4:$A$39,0)) -> 160 | D37: =C37-B37 -> 160 | E37: =D37*INDEX(WorkPackages!$F$4:$F$39,MATCH("WP-39",WorkPackages!$A$4:$A$39,0))*(1+Assumptions!$B$19) -> 499200 | F37: [new→R5] NEW — ShipStation, Flexport/SFN, Veeqo, CJ Dropshipping read connectors split out of WP-23 (R5)
A38: Sum of driver WPs | B38: =SUM(B30:B37) -> 2320 | C38: =SUM(C30:C37) -> 1500 | D38: =SUM(D30:D37) -> -820 | E38: =SUM(E30:E37) -> -2433600
A39: Check: Δ hours of drivers = Δ total hours (all other WPs unchanged) | D39: =IF(D38=D6,"OK — reconciles","CHECK") -> OK — reconciles
A40: Check: Δ INR of drivers = Δ full parity INR | E40: =IF(ABS(E38-D11)<1,"OK — reconciles","CHECK") -> OK — reconciles
A42: C. Release calendar & hours by release
A43: Release (v0.3 name) | B43: v0.2 weeks | C43: v0.3 weeks | D43: v0.2 hours | E43: v0.3 hours | F43: Comment
A44: R0 — Read-only pilot & foundations | B44: 8 | C44: =Assumptions!$B$26 -> 8 | D44: 1840 | E44: =Build_Summary!$B$5 -> 1840
A45: R1 — India-first unified profit core | B45: 14 | C45: =Assumptions!$B$27 -> 14 | D45: 4200 | E45: =Build_Summary!$B$6 -> 4200
A46: R2 — All markets & marketplaces | B46: 10 | C46: =Assumptions!$B$28 -> 14 | D46: 520 | E46: =Build_Summary!$B$7 -> 1240 | F46: Gained WP-23 (Walmart/eBay/TikTok Shop) and WP-38 (all Amazon marketplaces); WP-14 reduced; +4 weeks
A47: R3 — Operations | B47: 10 | C47: =Assumptions!$B$29 -> 10 | D47: 1540 | E47: =Build_Summary!$B$8 -> 1260 | F47: Lost WP-18 (review requests); WP-20 reduced
A48: R4 — Pricing automation (conditional) | B48: 10 | C48: =Assumptions!$B$30 -> 6 | D48: 1000 | E48: =Build_Summary!$B$9 -> 300 | F48: Lost WP-19 and WP-21 (PPC); repricer only; −4 weeks
A49: R5 — Extended operations connectors & clients | B49: 12 | C49: =Assumptions!$B$31 -> 10 | D49: 1300 | E49: =Build_Summary!$B$10 -> 740 | F49: Lost WP-23 to R2; gained WP-39 (ops connectors); −2 weeks
A50: ALL — cross-cutting | D50: 1600 | E50: =Build_Summary!$B$11 -> 1600
A51: TOTAL | B51: =SUM(B44:B50) -> 64 | C51: =SUM(C44:C50) -> 62 | D51: =SUM(D44:D50) -> 12000 | E51: =SUM(E44:E50) -> 11180
A53: Scope kept on purpose: ad SPEND is still read (WP-37, R1) as the Advertising cost line so net profit matches Sellerboard; LTV and repeat-customer reports stay (WP-14). History: v0.1 (2026-09-10) 10,280 h / ₹3,03,45,600 full parity → v0.2 12,000 h / ₹3,55,58,400 → v0.3 (this model).
